<?xml version='1.0' encoding='UTF-8' standalone='yes' ?>
<hierarchy rotation="0">
  <node index="0" text="" resource-id="" class="android.widget.FrameLayout" package="com.consumerapp_v1" content-desc="" checkable="false" checked="false" clickable="false" enabled="true" focusable="false" focused="false" scrollable="false" long-clickable="false" password="false" selected="false" visible-to-user="true" bounds="[0,0][768,1280]" drawing-order="0" hint="" display-id="0">
    <node index="0" text="" resource-id="" class="android.widget.LinearLayout" package="com.consumerapp_v1" content-desc="" checkable="false" checked="false" clickable="false" enabled="true" focusable="false" focused="false" scrollable="false" long-clickable="false" password="false" selected="false" visible-to-user="true" bounds="[0,0][768,1184]" drawing-order="1" hint="" display-id="0">
      <node index="0" text="" resource-id="" class="android.widget.FrameLayout" package="com.consumerapp_v1" content-desc="" checkable="false" checked="false" clickable="false" enabled="true" focusable="false" focused="false" scrollable="false" long-clickable="false" password="false" selected="false" visible-to-user="true" bounds="[0,48][768,1184]" drawing-order="2" hint="" display-id="0">
        <node index="0" text="" resource-id="com.consumerapp_v1:id/action_bar_root" class="android.widget.LinearLayout" package="com.consumerapp_v1" content-desc="" checkable="false" checked="false" clickable="false" enabled="true" focusable="false" focused="false" scrollable="false" long-clickable="false" password="false" selected="false" visible-to-user="true" bounds="[0,48][768,1184]" drawing-order="1" hint="" display-id="0">
          <node index="0" text="" resource-id="android:id/content" class="android.widget.FrameLayout" package="com.consumerapp_v1" content-desc="" checkable="false" checked="false" clickable="false" enabled="true" focusable="false" focused="false" scrollable="false" long-clickable="false" password="false" selected="false" visible-to-user="true" bounds="[0,48][768,1184]" drawing-order="2" hint="" display-id="0">
            <node index="0" text="" resource-id="" class="android.widget.FrameLayout" package="com.consumerapp_v1" content-desc="" checkable="false" checked="false" clickable="false" enabled="true" focusable="false" focused="false" scrollable="false" long-clickable="false" password="false" selected="false" visible-to-user="true" bounds="[0,48][768,1184]" drawing-order="1" hint="" display-id="0">
              <node index="0" text="" resource-id="" class="android.view.ViewGroup" package="com.consumerapp_v1" content-desc="" checkable="false" checked="false" clickable="false" enabled="true" focusable="false" focused="false" scrollable="false" long-clickable="false" password="false" selected="false" visible-to-user="true" bounds="[0,48][768,1184]" drawing-order="1" hint="" display-id="0">
                <node index="0" text="" resource-id="" class="android.view.ViewGroup" package="com.consumerapp_v1" content-desc="" checkable="false" checked="false" clickable="false" enabled="true" focusable="false" focused="false" scrollable="false" long-clickable="false" password="false" selected="false" visible-to-user="true" bounds="[0,48][768,1184]" drawing-order="1" hint="" display-id="0">
                  <node index="0" text="" resource-id="" class="android.view.ViewGroup" package="com.consumerapp_v1" content-desc="" checkable="false" checked="false" clickable="false" enabled="true" focusable="false" focused="false" scrollable="false" long-clickable="false" password="false" selected="false" visible-to-user="true" bounds="[0,48][768,1184]" drawing-order="1" hint="" display-id="0" />
                  <node index="1" text="" resource-id="" class="android.view.ViewGroup" package="com.consumerapp_v1" content-desc="" checkable="false" checked="false" clickable="false" enabled="true" focusable="false" focused="false" scrollable="false" long-clickable="false" password="false" selected="false" visible-to-user="true" bounds="[0,48][768,1184]" drawing-order="2" hint="" display-id="0">
                    <node index="0" text="" resource-id="" class="android.view.ViewGroup" package="com.consumerapp_v1" content-desc="" checkable="false" checked="false" clickable="false" enabled="true" focusable="false" focused="false" scrollable="false" long-clickable="false" password="false" selected="false" visible-to-user="true" bounds="[0,48][768,1184]" drawing-order="1" hint="" display-id="0">
                      <node index="1" text="" resource-id="" class="android.view.ViewGroup" package="com.consumerapp_v1" content-desc="" checkable="false" checked="false" clickable="false" enabled="true" focusable="false" focused="false" scrollable="false" long-clickable="false" password="false" selected="false" visible-to-user="true" bounds="[0,48][768,1184]" drawing-order="1" hint="" display-id="0">
                        <node index="0" text="" resource-id="" class="android.view.ViewGroup" package="com.consumerapp_v1" content-desc="" checkable="false" checked="false" clickable="false" enabled="true" focusable="false" focused="false" scrollable="false" long-clickable="false" password="false" selected="false" visible-to-user="true" bounds="[0,48][768,1184]" drawing-order="1" hint="" display-id="0">
                          <node index="0" text="" resource-id="" class="android.view.ViewGroup" package="com.consumerapp_v1" content-desc="" checkable="false" checked="false" clickable="false" enabled="true" focusable="false" focused="false" scrollable="false" long-clickable="false" password="false" selected="false" visible-to-user="true" bounds="[0,48][768,1184]" drawing-order="1" hint="" display-id="0">
                            <node index="0" text="" resource-id="" class="android.view.ViewGroup" package="com.consumerapp_v1" content-desc="" checkable="false" checked="false" clickable="false" enabled="true" focusable="false" focused="false" scrollable="false" long-clickable="false" password="false" selected="false" visible-to-user="true" bounds="[0,48][768,1184]" drawing-order="2" hint="" display-id="0">
                              <node index="0" text="" resource-id="" class="android.view.ViewGroup" package="com.consumerapp_v1" content-desc="" checkable="false" checked="false" clickable="false" enabled="true" focusable="false" focused="false" scrollable="false" long-clickable="false" password="false" selected="false" visible-to-user="true" bounds="[0,48][768,1184]" drawing-order="1" hint="" display-id="0">
                                <node index="0" text="" resource-id="" class="android.view.ViewGroup" package="com.consumerapp_v1" content-desc="" checkable="false" checked="false" clickable="false" enabled="true" focusable="false" focused="false" scrollable="false" long-clickable="false" password="false" selected="false" visible-to-user="true" bounds="[0,48][768,1184]" drawing-order="1" hint="" display-id="0" />
                                <node index="1" text="" resource-id="" class="android.view.ViewGroup" package="com.consumerapp_v1" content-desc="" checkable="false" checked="false" clickable="false" enabled="true" focusable="false" focused="false" scrollable="false" long-clickable="false" password="false" selected="false" visible-to-user="true" bounds="[0,48][768,1184]" drawing-order="2" hint="" display-id="0">
                                  <node index="0" text="" resource-id="" class="android.view.ViewGroup" package="com.consumerapp_v1" content-desc="" checkable="false" checked="false" clickable="false" enabled="true" focusable="false" focused="false" scrollable="false" long-clickable="false" password="false" selected="false" visible-to-user="true" bounds="[0,48][768,1184]" drawing-order="1" hint="" display-id="0">
                                    <node index="0" text="" resource-id="" class="android.widget.LinearLayout" package="com.consumerapp_v1" content-desc="" checkable="false" checked="false" clickable="false" enabled="true" focusable="false" focused="false" scrollable="false" long-clickable="false" password="false" selected="false" visible-to-user="true" bounds="[0,48][768,160]" drawing-order="2" hint="" display-id="0">
                                      <node index="0" text="" resource-id="" class="android.view.ViewGroup" package="com.consumerapp_v1" content-desc="" checkable="false" checked="false" clickable="false" enabled="true" focusable="false" focused="false" scrollable="false" long-clickable="false" password="false" selected="false" visible-to-user="true" bounds="[0,48][768,160]" drawing-order="1" hint="" display-id="0">
                                        <node index="0" text="" resource-id="" class="android.view.ViewGroup" package="com.consumerapp_v1" content-desc="" checkable="false" checked="false" clickable="false" enabled="true" focusable="false" focused="false" scrollable="false" long-clickable="false" password="false" selected="false" visible-to-user="true" bounds="[32,77][342,131]" drawing-order="1" hint="" display-id="0">
                                          <node index="0" text="" resource-id="" class="android.view.ViewGroup" package="com.consumerapp_v1" content-desc="Close button" checkable="false" checked="false" clickable="true" enabled="true" focusable="true" focused="false" scrollable="false" long-clickable="false" password="false" selected="false" visible-to-user="true" bounds="[32,78][84,130]" drawing-order="1" hint="" display-id="0">
                                            <node index="0" text="" resource-id="" class="android.widget.ImageView" package="com.consumerapp_v1" content-desc="" checkable="false" checked="false" clickable="false" enabled="true" focusable="false" focused="false" scrollable="false" long-clickable="false" password="false" selected="false" visible-to-user="true" bounds="[32,78][84,130]" drawing-order="1" hint="" display-id="0" />
                                          </node>
                                          <node index="1" text="Add a new pet" resource-id="" class="android.widget.TextView" package="com.consumerapp_v1" content-desc="" checkable="false" checked="false" clickable="false" enabled="true" focusable="false" focused="false" scrollable="false" long-clickable="false" password="false" selected="false" visible-to-user="true" bounds="[116,82][331,126]" drawing-order="2" hint="" display-id="0" />
                                          <node index="2" text="" resource-id="" class="android.view.View" package="com.consumerapp_v1" content-desc="" checkable="false" checked="false" clickable="false" enabled="true" focusable="false" focused="false" scrollable="false" long-clickable="false" password="false" selected="false" visible-to-user="true" bounds="[331,77][342,131]" drawing-order="3" hint="" display-id="0" />
                                        </node>
                                        <node index="1" text="" resource-id="" class="android.view.ViewGroup" package="com.consumerapp_v1" content-desc="" checkable="false" checked="false" clickable="false" enabled="true" focusable="false" focused="false" scrollable="false" long-clickable="false" password="false" selected="false" visible-to-user="true" bounds="[654,50][736,158]" drawing-order="2" hint="" display-id="0">
                                          <node index="0" text="" resource-id="" class="android.view.ViewGroup" package="com.consumerapp_v1" content-desc="" checkable="false" checked="false" clickable="false" enabled="true" focusable="false" focused="false" scrollable="false" long-clickable="false" password="false" selected="false" visible-to-user="true" bounds="[654,50][736,158]" drawing-order="1" hint="" display-id="0">
                                            <node index="0" text="" resource-id="" class="android.view.ViewGroup" package="com.consumerapp_v1" content-desc="cart button  there are no items in your cart" checkable="false" checked="false" clickable="false" enabled="true" focusable="true" focused="false" scrollable="false" long-clickable="false" password="false" selected="false" visible-to-user="true" bounds="[654,50][736,158]" drawing-order="1" hint="" display-id="0">
                                              <node index="0" text="" resource-id="" class="android.view.ViewGroup" package="com.consumerapp_v1" content-desc="" checkable="false" checked="false" clickable="false" enabled="true" focusable="false" focused="false" scrollable="false" long-clickable="false" password="false" selected="false" visible-to-user="true" bounds="[664,74][716,126]" drawing-order="1" hint="" display-id="0">
                                                <node index="0" text="" resource-id="" class="android.widget.ImageView" package="com.consumerapp_v1" content-desc="" checkable="false" checked="false" clickable="false" enabled="true" focusable="false" focused="false" scrollable="false" long-clickable="false" password="false" selected="false" visible-to-user="true" bounds="[664,74][716,126]" drawing-order="1" hint="" display-id="0" />
                                              </node>
                                            </node>
                                          </node>
                                        </node>
                                      </node>
                                    </node>
                                    <node index="1" text="" resource-id="" class="android.view.ViewGroup" package="com.consumerapp_v1" content-desc="" checkable="false" checked="false" clickable="false" enabled="true" focusable="false" focused="false" scrollable="false" long-clickable="false" password="false" selected="false" visible-to-user="true" bounds="[0,160][768,1184]" drawing-order="1" hint="" display-id="0">
                                      <node index="0" text="" resource-id="" class="android.view.ViewGroup" package="com.consumerapp_v1" content-desc="" checkable="false" checked="false" clickable="false" enabled="true" focusable="false" focused="false" scrollable="false" long-clickable="false" password="false" selected="false" visible-to-user="true" bounds="[0,160][768,1184]" drawing-order="1" hint="" display-id="0">
                                        <node index="0" text="" resource-id="" class="android.view.ViewGroup" package="com.consumerapp_v1" content-desc="" checkable="false" checked="false" clickable="false" enabled="true" focusable="false" focused="false" scrollable="false" long-clickable="false" password="false" selected="false" visible-to-user="true" bounds="[0,160][768,1184]" drawing-order="1" hint="" display-id="0" />
                                        <node index="1" text="" resource-id="" class="android.widget.HorizontalScrollView" package="com.consumerapp_v1" content-desc="" checkable="false" checked="false" clickable="false" enabled="true" focusable="true" focused="false" scrollable="false" long-clickable="false" password="false" selected="false" visible-to-user="true" bounds="[0,160][768,1064]" drawing-order="2" hint="" display-id="0">
                                          <node index="0" text="" resource-id="" class="android.view.ViewGroup" package="com.consumerapp_v1" content-desc="" checkable="false" checked="false" clickable="false" enabled="true" focusable="false" focused="false" scrollable="false" long-clickable="false" password="false" selected="false" visible-to-user="true" bounds="[0,160][768,1064]" drawing-order="1" hint="" display-id="0">
                                            <node index="0" text="What type of pet would you like to add?" resource-id="" class="android.widget.TextView" package="com.consumerapp_v1" content-desc="What type of pet would you like to add?" checkable="false" checked="false" clickable="false" enabled="true" focusable="false" focused="false" scrollable="false" long-clickable="false" password="false" selected="false" visible-to-user="true" bounds="[18,230][749,331]" drawing-order="1" hint="" display-id="0" />
                                            <node index="1" text="" resource-id="" class="android.widget.ScrollView" package="com.consumerapp_v1" content-desc="" checkable="false" checked="false" clickable="false" enabled="true" focusable="true" focused="false" scrollable="true" long-clickable="false" password="false" selected="false" visible-to-user="true" bounds="[20,371][748,1064]" drawing-order="2" hint="" display-id="0">
                                              <node index="0" text="" resource-id="" class="android.view.ViewGroup" package="com.consumerapp_v1" content-desc="" checkable="false" checked="false" clickable="false" enabled="true" focusable="false" focused="false" scrollable="false" long-clickable="false" password="false" selected="false" visible-to-user="true" bounds="[20,371][748,1064]" drawing-order="1" hint="" display-id="0">
                                                <node index="0" text="" resource-id="" class="android.view.ViewGroup" package="com.consumerapp_v1" content-desc="Reptile" checkable="false" checked="false" clickable="true" enabled="true" focusable="true" focused="false" scrollable="false" long-clickable="false" password="false" selected="false" visible-to-user="true" bounds="[28,379][194,588]" drawing-order="1" hint="" display-id="0">
                                                  <node index="0" text="" resource-id="" class="android.view.ViewGroup" package="com.consumerapp_v1" content-desc="" checkable="false" checked="false" clickable="false" enabled="true" focusable="false" focused="false" scrollable="false" long-clickable="false" password="false" selected="false" visible-to-user="true" bounds="[28,379][194,545]" drawing-order="1" hint="" display-id="0" />
                                                  <node index="1" text="" resource-id="" class="android.view.ViewGroup" package="com.consumerapp_v1" content-desc="" checkable="false" checked="false" clickable="false" enabled="true" focusable="false" focused="false" scrollable="false" long-clickable="false" password="false" selected="false" visible-to-user="true" bounds="[78,442][144,482]" drawing-order="2" hint="" display-id="0">
                                                    <node index="0" text="" resource-id="" class="com.horcrux.svg.SvgView" package="com.consumerapp_v1" content-desc="" checkable="false" checked="false" clickable="false" enabled="true" focusable="false" focused="false" scrollable="false" long-clickable="false" password="false" selected="false" visible-to-user="true" bounds="[78,442][144,482]" drawing-order="1" hint="" display-id="0">
                                                      <node index="0" text="" resource-id="" class="com.horcrux.svg.GroupView" package="com.consumerapp_v1" content-desc="" checkable="false" checked="false" clickable="false" enabled="true" focusable="false" focused="false" scrollable="false" long-clickable="false" password="false" selected="false" visible-to-user="true" bounds="[78,442][144,482]" drawing-order="0" hint="" display-id="0">
                                                        <node index="0" text="" resource-id="" class="com.horcrux.svg.PathView" package="com.consumerapp_v1" content-desc="" checkable="false" checked="false" clickable="false" enabled="true" focusable="false" focused="false" scrollable="false" long-clickable="false" password="false" selected="false" visible-to-user="true" bounds="[78,442][144,482]" drawing-order="1" hint="" display-id="0" />
                                                      </node>
                                                    </node>
                                                  </node>
                                                  <node index="2" text="Reptile" resource-id="" class="android.widget.TextView" package="com.consumerapp_v1" content-desc="" checkable="false" checked="false" clickable="false" enabled="true" focusable="false" focused="false" scrollable="false" long-clickable="false" password="false" selected="false" visible-to-user="true" bounds="[71,555][151,588]" drawing-order="3" hint="" display-id="0" />
                                                </node>
                                                <node index="1" text="" resource-id="" class="android.view.ViewGroup" package="com.consumerapp_v1" content-desc="Horse" checkable="false" checked="false" clickable="true" enabled="true" focusable="true" focused="false" scrollable="false" long-clickable="false" password="false" selected="false" visible-to-user="true" bounds="[210,379][376,588]" drawing-order="2" hint="" display-id="0">
                                                  <node index="0" text="" resource-id="" class="android.view.ViewGroup" package="com.consumerapp_v1" content-desc="" checkable="false" checked="false" clickable="false" enabled="true" focusable="false" focused="false" scrollable="false" long-clickable="false" password="false" selected="false" visible-to-user="true" bounds="[210,379][376,545]" drawing-order="1" hint="" display-id="0" />
                                                  <node index="1" text="" resource-id="" class="android.view.ViewGroup" package="com.consumerapp_v1" content-desc="" checkable="false" checked="false" clickable="false" enabled="true" focusable="false" focused="false" scrollable="false" long-clickable="false" password="false" selected="false" visible-to-user="true" bounds="[266,438][320,486]" drawing-order="2" hint="" display-id="0">
                                                    <node index="0" text="" resource-id="" class="com.horcrux.svg.SvgView" package="com.consumerapp_v1" content-desc="" checkable="false" checked="false" clickable="false" enabled="true" focusable="false" focused="false" scrollable="false" long-clickable="false" password="false" selected="false" visible-to-user="true" bounds="[266,438][320,486]" drawing-order="1" hint="" display-id="0">
                                                      <node index="0" text="" resource-id="" class="com.horcrux.svg.GroupView" package="com.consumerapp_v1" content-desc="" checkable="false" checked="false" clickable="false" enabled="true" focusable="false" focused="false" scrollable="false" long-clickable="false" password="false" selected="false" visible-to-user="true" bounds="[266,438][320,486]" drawing-order="0" hint="" display-id="0">
                                                        <node index="0" text="" resource-id="" class="com.horcrux.svg.PathView" package="com.consumerapp_v1" content-desc="" checkable="false" checked="false" clickable="false" enabled="true" focusable="false" focused="false" scrollable="false" long-clickable="false" password="false" selected="false" visible-to-user="true" bounds="[266,438][320,486]" drawing-order="1" hint="" display-id="0" />
                                                      </node>
                                                    </node>
                                                  </node>
                                                  <node index="2" text="Horse" resource-id="" class="android.widget.TextView" package="com.consumerapp_v1" content-desc="" checkable="false" checked="false" clickable="false" enabled="true" focusable="false" focused="false" scrollable="false" long-clickable="false" password="false" selected="false" visible-to-user="true" bounds="[259,555][327,588]" drawing-order="3" hint="" display-id="0" />
                                                </node>
                                                <node index="2" text="" resource-id="" class="android.view.ViewGroup" package="com.consumerapp_v1" content-desc="Cat Selected" checkable="false" checked="false" clickable="true" enabled="true" focusable="true" focused="false" scrollable="false" long-clickable="false" password="false" selected="false" visible-to-user="true" bounds="[392,379][558,588]" drawing-order="3" hint="" display-id="0">
                                                  <node index="0" text="" resource-id="" class="android.view.ViewGroup" package="com.consumerapp_v1" content-desc="" checkable="false" checked="false" clickable="false" enabled="true" focusable="false" focused="false" scrollable="false" long-clickable="false" password="false" selected="false" visible-to-user="true" bounds="[392,379][558,545]" drawing-order="1" hint="" display-id="0" />
                                                  <node index="1" text="" resource-id="" class="android.view.ViewGroup" package="com.consumerapp_v1" content-desc="" checkable="false" checked="false" clickable="false" enabled="true" focusable="false" focused="false" scrollable="false" long-clickable="false" password="false" selected="false" visible-to-user="true" bounds="[451,440][499,484]" drawing-order="2" hint="" display-id="0">
                                                    <node index="0" text="" resource-id="" class="com.horcrux.svg.SvgView" package="com.consumerapp_v1" content-desc="" checkable="false" checked="false" clickable="false" enabled="true" focusable="false" focused="false" scrollable="false" long-clickable="false" password="false" selected="false" visible-to-user="true" bounds="[451,440][499,484]" drawing-order="1" hint="" display-id="0">
                                                      <node index="0" text="" resource-id="" class="com.horcrux.svg.GroupView" package="com.consumerapp_v1" content-desc="" checkable="false" checked="false" clickable="false" enabled="true" focusable="false" focused="false" scrollable="false" long-clickable="false" password="false" selected="false" visible-to-user="true" bounds="[451,440][499,484]" drawing-order="0" hint="" display-id="0">
                                                        <node index="0" text="" resource-id="" class="com.horcrux.svg.PathView" package="com.consumerapp_v1" content-desc="" checkable="false" checked="false" clickable="false" enabled="true" focusable="false" focused="false" scrollable="false" long-clickable="false" password="false" selected="false" visible-to-user="true" bounds="[451,440][499,484]" drawing-order="1" hint="" display-id="0" />
                                                      </node>
                                                    </node>
                                                  </node>
                                                  <node index="2" text="Cat" resource-id="" class="android.widget.TextView" package="com.consumerapp_v1" content-desc="" checkable="false" checked="false" clickable="false" enabled="true" focusable="false" focused="false" scrollable="false" long-clickable="false" password="false" selected="false" visible-to-user="true" bounds="[455,555][494,588]" drawing-order="3" hint="" display-id="0" />
                                                </node>
                                                <node index="3" text="" resource-id="" class="android.view.ViewGroup" package="com.consumerapp_v1" content-desc="Fish" checkable="false" checked="false" clickable="true" enabled="true" focusable="true" focused="false" scrollable="false" long-clickable="false" password="false" selected="false" visible-to-user="true" bounds="[574,379][740,588]" drawing-order="4" hint="" display-id="0">
                                                  <node index="0" text="" resource-id="" class="android.view.ViewGroup" package="com.consumerapp_v1" content-desc="" checkable="false" checked="false" clickable="false" enabled="true" focusable="false" focused="false" scrollable="false" long-clickable="false" password="false" selected="false" visible-to-user="true" bounds="[574,379][740,545]" drawing-order="1" hint="" display-id="0" />
                                                  <node index="1" text="" resource-id="" class="android.view.ViewGroup" package="com.consumerapp_v1" content-desc="" checkable="false" checked="false" clickable="false" enabled="true" focusable="false" focused="false" scrollable="false" long-clickable="false" password="false" selected="false" visible-to-user="true" bounds="[627,435][687,489]" drawing-order="2" hint="" display-id="0">
                                                    <node index="0" text="" resource-id="" class="com.horcrux.svg.SvgView" package="com.consumerapp_v1" content-desc="" checkable="false" checked="false" clickable="false" enabled="true" focusable="false" focused="false" scrollable="false" long-clickable="false" password="false" selected="false" visible-to-user="true" bounds="[627,435][687,489]" drawing-order="1" hint="" display-id="0">
                                                      <node index="0" text="" resource-id="" class="com.horcrux.svg.GroupView" package="com.consumerapp_v1" content-desc="" checkable="false" checked="false" clickable="false" enabled="true" focusable="false" focused="false" scrollable="false" long-clickable="false" password="false" selected="false" visible-to-user="true" bounds="[627,435][687,489]" drawing-order="0" hint="" display-id="0">
                                                        <node index="0" text="" resource-id="" class="com.horcrux.svg.PathView" package="com.consumerapp_v1" content-desc="" checkable="false" checked="false" clickable="false" enabled="true" focusable="false" focused="false" scrollable="false" long-clickable="false" password="false" selected="false" visible-to-user="true" bounds="[627,435][687,489]" drawing-order="1" hint="" display-id="0" />
                                                      </node>
                                                    </node>
                                                  </node>
                                                  <node index="2" text="Fish" resource-id="" class="android.widget.TextView" package="com.consumerapp_v1" content-desc="" checkable="false" checked="false" clickable="false" enabled="true" focusable="false" focused="false" scrollable="false" long-clickable="false" password="false" selected="false" visible-to-user="true" bounds="[633,555][680,588]" drawing-order="3" hint="" display-id="0" />
                                                </node>
                                                <node index="4" text="" resource-id="" class="android.view.ViewGroup" package="com.consumerapp_v1" content-desc="Bird" checkable="false" checked="false" clickable="true" enabled="true" focusable="true" focused="false" scrollable="false" long-clickable="false" password="false" selected="false" visible-to-user="true" bounds="[28,616][194,825]" drawing-order="5" hint="" display-id="0">
                                                  <node index="0" text="" resource-id="" class="android.view.ViewGroup" package="com.consumerapp_v1" content-desc="" checkable="false" checked="false" clickable="false" enabled="true" focusable="false" focused="false" scrollable="false" long-clickable="false" password="false" selected="false" visible-to-user="true" bounds="[28,616][194,782]" drawing-order="1" hint="" display-id="0" />
                                                  <node index="1" text="" resource-id="" class="android.view.ViewGroup" package="com.consumerapp_v1" content-desc="" checkable="false" checked="false" clickable="false" enabled="true" focusable="false" focused="false" scrollable="false" long-clickable="false" password="false" selected="false" visible-to-user="true" bounds="[84,678][138,720]" drawing-order="2" hint="" display-id="0">
                                                    <node index="0" text="" resource-id="" class="com.horcrux.svg.SvgView" package="com.consumerapp_v1" content-desc="" checkable="false" checked="false" clickable="false" enabled="true" focusable="false" focused="false" scrollable="false" long-clickable="false" password="false" selected="false" visible-to-user="true" bounds="[84,678][138,720]" drawing-order="1" hint="" display-id="0">
                                                      <node index="0" text="" resource-id="" class="com.horcrux.svg.GroupView" package="com.consumerapp_v1" content-desc="" checkable="false" checked="false" clickable="false" enabled="true" focusable="false" focused="false" scrollable="false" long-clickable="false" password="false" selected="false" visible-to-user="true" bounds="[84,678][138,720]" drawing-order="0" hint="" display-id="0">
                                                        <node index="0" text="" resource-id="" class="com.horcrux.svg.PathView" package="com.consumerapp_v1" content-desc="" checkable="false" checked="false" clickable="false" enabled="true" focusable="false" focused="false" scrollable="false" long-clickable="false" password="false" selected="false" visible-to-user="true" bounds="[84,678][138,720]" drawing-order="1" hint="" display-id="0" />
                                                      </node>
                                                    </node>
                                                  </node>
                                                  <node index="2" text="Bird" resource-id="" class="android.widget.TextView" package="com.consumerapp_v1" content-desc="" checkable="false" checked="false" clickable="false" enabled="true" focusable="false" focused="false" scrollable="false" long-clickable="false" password="false" selected="false" visible-to-user="true" bounds="[88,792][134,825]" drawing-order="3" hint="" display-id="0" />
                                                </node>
                                                <node index="5" text="" resource-id="" class="android.view.ViewGroup" package="com.consumerapp_v1" content-desc="Goat" checkable="false" checked="false" clickable="true" enabled="true" focusable="true" focused="false" scrollable="false" long-clickable="false" password="false" selected="false" visible-to-user="true" bounds="[210,616][376,825]" drawing-order="6" hint="" display-id="0">
                                                  <node index="0" text="" resource-id="" class="android.view.ViewGroup" package="com.consumerapp_v1" content-desc="" checkable="false" checked="false" clickable="false" enabled="true" focusable="false" focused="false" scrollable="false" long-clickable="false" password="false" selected="false" visible-to-user="true" bounds="[210,616][376,782]" drawing-order="1" hint="" display-id="0" />
                                                  <node index="1" text="" resource-id="" class="android.view.ViewGroup" package="com.consumerapp_v1" content-desc="" checkable="false" checked="false" clickable="false" enabled="true" focusable="false" focused="false" scrollable="false" long-clickable="false" password="false" selected="false" visible-to-user="true" bounds="[260,669][326,729]" drawing-order="2" hint="" display-id="0">
                                                    <node index="0" text="" resource-id="" class="com.horcrux.svg.SvgView" package="com.consumerapp_v1" content-desc="" checkable="false" checked="false" clickable="false" enabled="true" focusable="false" focused="false" scrollable="false" long-clickable="false" password="false" selected="false" visible-to-user="true" bounds="[260,669][326,729]" drawing-order="1" hint="" display-id="0">
                                                      <node index="0" text="" resource-id="" class="com.horcrux.svg.GroupView" package="com.consumerapp_v1" content-desc="" checkable="false" checked="false" clickable="false" enabled="true" focusable="false" focused="false" scrollable="false" long-clickable="false" password="false" selected="false" visible-to-user="true" bounds="[260,669][326,729]" drawing-order="0" hint="" display-id="0">
                                                        <node index="0" text="" resource-id="" class="com.horcrux.svg.GroupView" package="com.consumerapp_v1" content-desc="" checkable="false" checked="false" clickable="false" enabled="true" focusable="false" focused="false" scrollable="false" long-clickable="false" password="false" selected="false" visible-to-user="true" bounds="[260,669][326,729]" drawing-order="2" hint="" display-id="0">
                                                          <node index="0" text="" resource-id="" class="com.horcrux.svg.GroupView" package="com.consumerapp_v1" content-desc="" checkable="false" checked="false" clickable="false" enabled="true" focusable="false" focused="false" scrollable="false" long-clickable="false" password="false" selected="false" visible-to-user="true" bounds="[260,669][326,729]" drawing-order="2" hint="" display-id="0">
                                                            <node index="0" text="" resource-id="" class="com.horcrux.svg.PathView" package="com.consumerapp_v1" content-desc="" checkable="false" checked="false" clickable="false" enabled="true" focusable="false" focused="false" scrollable="false" long-clickable="false" password="false" selected="false" visible-to-user="true" bounds="[260,669][326,729]" drawing-order="1" hint="" display-id="0" />
                                                          </node>
                                                          <node index="1" text="" resource-id="" class="com.horcrux.svg.PathView" package="com.consumerapp_v1" content-desc="" checkable="false" checked="false" clickable="false" enabled="true" focusable="false" focused="false" scrollable="false" long-clickable="false" password="false" selected="false" visible-to-user="true" bounds="[260,669][326,729]" drawing-order="1" hint="" display-id="0" />
                                                        </node>
                                                        <node index="2" text="" resource-id="" class="com.horcrux.svg.PathView" package="com.consumerapp_v1" content-desc="" checkable="false" checked="false" clickable="false" enabled="true" focusable="false" focused="false" scrollable="false" long-clickable="false" password="false" selected="false" visible-to-user="true" bounds="[268,712][279,729]" drawing-order="3" hint="" display-id="0" />
                                                      </node>
                                                    </node>
                                                  </node>
                                                  <node index="2" text="Goat" resource-id="" class="android.widget.TextView" package="com.consumerapp_v1" content-desc="" checkable="false" checked="false" clickable="false" enabled="true" focusable="false" focused="false" scrollable="false" long-clickable="false" password="false" selected="false" visible-to-user="true" bounds="[266,792][320,825]" drawing-order="3" hint="" display-id="0" />
                                                </node>
                                                <node index="6" text="" resource-id="" class="android.view.ViewGroup" package="com.consumerapp_v1" content-desc="Dog" checkable="false" checked="false" clickable="true" enabled="true" focusable="true" focused="false" scrollable="false" long-clickable="false" password="false" selected="false" visible-to-user="true" bounds="[392,616][558,825]" drawing-order="7" hint="" display-id="0">
                                                  <node index="0" text="" resource-id="" class="android.view.ViewGroup" package="com.consumerapp_v1" content-desc="" checkable="false" checked="false" clickable="false" enabled="true" focusable="false" focused="false" scrollable="false" long-clickable="false" password="false" selected="false" visible-to-user="true" bounds="[392,616][558,782]" drawing-order="1" hint="" display-id="0" />
                                                  <node index="1" text="" resource-id="" class="android.view.ViewGroup" package="com.consumerapp_v1" content-desc="" checkable="false" checked="false" clickable="false" enabled="true" focusable="false" focused="false" scrollable="false" long-clickable="false" password="false" selected="false" visible-to-user="true" bounds="[451,677][499,721]" drawing-order="2" hint="" display-id="0">
                                                    <node index="0" text="" resource-id="" class="com.horcrux.svg.SvgView" package="com.consumerapp_v1" content-desc="" checkable="false" checked="false" clickable="false" enabled="true" focusable="false" focused="false" scrollable="false" long-clickable="false" password="false" selected="false" visible-to-user="true" bounds="[451,677][499,721]" drawing-order="1" hint="" display-id="0">
                                                      <node index="0" text="" resource-id="" class="com.horcrux.svg.GroupView" package="com.consumerapp_v1" content-desc="" checkable="false" checked="false" clickable="false" enabled="true" focusable="false" focused="false" scrollable="false" long-clickable="false" password="false" selected="false" visible-to-user="true" bounds="[451,677][499,721]" drawing-order="0" hint="" display-id="0">
                                                        <node index="0" text="" resource-id="" class="com.horcrux.svg.PathView" package="com.consumerapp_v1" content-desc="" checkable="false" checked="false" clickable="false" enabled="true" focusable="false" focused="false" scrollable="false" long-clickable="false" password="false" selected="false" visible-to-user="true" bounds="[451,677][499,721]" drawing-order="1" hint="" display-id="0" />
                                                      </node>
                                                    </node>
                                                  </node>
                                                  <node index="2" text="Dog" resource-id="" class="android.widget.TextView" package="com.consumerapp_v1" content-desc="" checkable="false" checked="false" clickable="false" enabled="true" focusable="false" focused="false" scrollable="false" long-clickable="false" password="false" selected="false" visible-to-user="true" bounds="[452,792][498,825]" drawing-order="3" hint="" display-id="0" />
                                                </node>
                                                <node index="7" text="" resource-id="" class="android.view.ViewGroup" package="com.consumerapp_v1" content-desc="Chicken" checkable="false" checked="false" clickable="true" enabled="true" focusable="true" focused="false" scrollable="false" long-clickable="false" password="false" selected="false" visible-to-user="true" bounds="[574,616][740,825]" drawing-order="8" hint="" display-id="0">
                                                  <node index="0" text="" resource-id="" class="android.view.ViewGroup" package="com.consumerapp_v1" content-desc="" checkable="false" checked="false" clickable="false" enabled="true" focusable="false" focused="false" scrollable="false" long-clickable="false" password="false" selected="false" visible-to-user="true" bounds="[574,616][740,782]" drawing-order="1" hint="" display-id="0" />
                                                  <node index="1" text="" resource-id="" class="android.view.ViewGroup" package="com.consumerapp_v1" content-desc="" checkable="false" checked="false" clickable="false" enabled="true" focusable="false" focused="false" scrollable="false" long-clickable="false" password="false" selected="false" visible-to-user="true" bounds="[628,667][686,731]" drawing-order="2" hint="" display-id="0">
                                                    <node index="0" text="" resource-id="" class="com.horcrux.svg.SvgView" package="com.consumerapp_v1" content-desc="" checkable="false" checked="false" clickable="false" enabled="true" focusable="false" focused="false" scrollable="false" long-clickable="false" password="false" selected="false" visible-to-user="true" bounds="[628,667][686,731]" drawing-order="1" hint="" display-id="0">
                                                      <node index="0" text="" resource-id="" class="com.horcrux.svg.GroupView" package="com.consumerapp_v1" content-desc="" checkable="false" checked="false" clickable="false" enabled="true" focusable="false" focused="false" scrollable="false" long-clickable="false" password="false" selected="false" visible-to-user="true" bounds="[628,667][686,731]" drawing-order="0" hint="" display-id="0">
                                                        <node index="0" text="" resource-id="" class="com.horcrux.svg.PathView" package="com.consumerapp_v1" content-desc="" checkable="false" checked="false" clickable="false" enabled="true" focusable="false" focused="false" scrollable="false" long-clickable="false" password="false" selected="false" visible-to-user="true" bounds="[628,667][686,716]" drawing-order="1" hint="" display-id="0" />
                                                        <node index="1" text="" resource-id="" class="com.horcrux.svg.PathView" package="com.consumerapp_v1" content-desc="" checkable="false" checked="false" clickable="false" enabled="true" focusable="false" focused="false" scrollable="false" long-clickable="false" password="false" selected="false" visible-to-user="true" bounds="[680,690][686,701]" drawing-order="4" hint="" display-id="0" />
                                                        <node index="2" text="" resource-id="" class="com.horcrux.svg.PathView" package="com.consumerapp_v1" content-desc="" checkable="false" checked="false" clickable="false" enabled="true" focusable="false" focused="false" scrollable="false" long-clickable="false" password="false" selected="false" visible-to-user="true" bounds="[628,715][648,731]" drawing-order="2" hint="" display-id="0" />
                                                        <node index="3" text="" resource-id="" class="com.horcrux.svg.PathView" package="com.consumerapp_v1" content-desc="" checkable="false" checked="false" clickable="false" enabled="true" focusable="false" focused="false" scrollable="false" long-clickable="false" password="false" selected="false" visible-to-user="true" bounds="[654,719][671,731]" drawing-order="3" hint="" display-id="0" />
                                                      </node>
                                                    </node>
                                                  </node>
                                                  <node index="2" text="Chicken" resource-id="" class="android.widget.TextView" package="com.consumerapp_v1" content-desc="" checkable="false" checked="false" clickable="false" enabled="true" focusable="false" focused="false" scrollable="false" long-clickable="false" password="false" selected="false" visible-to-user="true" bounds="[611,792][703,825]" drawing-order="3" hint="" display-id="0" />
                                                </node>
                                                <node index="8" text="" resource-id="" class="android.view.ViewGroup" package="com.consumerapp_v1" content-desc="Small Animal" checkable="false" checked="false" clickable="true" enabled="true" focusable="true" focused="false" scrollable="false" long-clickable="false" password="false" selected="false" visible-to-user="true" bounds="[28,853][194,1062]" drawing-order="9" hint="" display-id="0">
                                                  <node index="0" text="" resource-id="" class="android.view.ViewGroup" package="com.consumerapp_v1" content-desc="" checkable="false" checked="false" clickable="false" enabled="true" focusable="false" focused="false" scrollable="false" long-clickable="false" password="false" selected="false" visible-to-user="true" bounds="[28,853][194,1019]" drawing-order="1" hint="" display-id="0" />
                                                  <node index="1" text="" resource-id="" class="android.view.ViewGroup" package="com.consumerapp_v1" content-desc="" checkable="false" checked="false" clickable="false" enabled="true" focusable="false" focused="false" scrollable="false" long-clickable="false" password="false" selected="false" visible-to-user="true" bounds="[86,906][136,966]" drawing-order="2" hint="" display-id="0">
                                                    <node index="0" text="" resource-id="" class="com.horcrux.svg.SvgView" package="com.consumerapp_v1" content-desc="" checkable="false" checked="false" clickable="false" enabled="true" focusable="false" focused="false" scrollable="false" long-clickable="false" password="false" selected="false" visible-to-user="true" bounds="[86,906][136,966]" drawing-order="1" hint="" display-id="0">
                                                      <node index="0" text="" resource-id="" class="com.horcrux.svg.GroupView" package="com.consumerapp_v1" content-desc="" checkable="false" checked="false" clickable="false" enabled="true" focusable="false" focused="false" scrollable="false" long-clickable="false" password="false" selected="false" visible-to-user="true" bounds="[86,906][136,966]" drawing-order="0" hint="" display-id="0">
                                                        <node index="0" text="" resource-id="" class="com.horcrux.svg.PathView" package="com.consumerapp_v1" content-desc="" checkable="false" checked="false" clickable="false" enabled="true" focusable="false" focused="false" scrollable="false" long-clickable="false" password="false" selected="false" visible-to-user="true" bounds="[86,906][136,966]" drawing-order="1" hint="" display-id="0" />
                                                      </node>
                                                    </node>
                                                  </node>
                                                  <node index="2" text="Small Animal" resource-id="" class="android.widget.TextView" package="com.consumerapp_v1" content-desc="" checkable="false" checked="false" clickable="false" enabled="true" focusable="false" focused="false" scrollable="false" long-clickable="false" password="false" selected="false" visible-to-user="true" bounds="[36,1029][185,1062]" drawing-order="3" hint="" display-id="0" />
                                                </node>
                                              </node>
                                            </node>
                                          </node>
                                        </node>
                                        <node index="2" text="" resource-id="" class="android.view.ViewGroup" package="com.consumerapp_v1" content-desc="" checkable="false" checked="false" clickable="false" enabled="true" focusable="false" focused="false" scrollable="false" long-clickable="false" password="false" selected="false" visible-to-user="true" bounds="[0,984][768,1104]" drawing-order="3" hint="" display-id="0" />
                                        <node index="3" text="" resource-id="" class="android.view.ViewGroup" package="com.consumerapp_v1" content-desc="Step 1 slash 10" checkable="false" checked="false" clickable="true" enabled="false" focusable="true" focused="false" scrollable="false" long-clickable="false" password="false" selected="false" visible-to-user="true" bounds="[257,996][511,1092]" drawing-order="4" hint="" display-id="0">
                                          <node index="0" text="Step 1/10" resource-id="" class="android.widget.TextView" package="com.consumerapp_v1" content-desc="" checkable="false" checked="false" clickable="false" enabled="true" focusable="false" focused="false" scrollable="false" long-clickable="false" password="false" selected="false" visible-to-user="true" bounds="[322,1029][445,1059]" drawing-order="1" hint="" display-id="0" />
                                        </node>
                                        <node index="4" text="" resource-id="" class="android.view.ViewGroup" package="com.consumerapp_v1" content-desc="NEXT button" checkable="false" checked="false" clickable="true" enabled="true" focusable="true" focused="false" scrollable="false" long-clickable="false" password="false" selected="false" visible-to-user="true" bounds="[515,996][768,1092]" drawing-order="5" hint="" display-id="0">
                                          <node index="0" text="NEXT" resource-id="" class="android.widget.TextView" package="com.consumerapp_v1" content-desc="" checkable="false" checked="false" clickable="false" enabled="true" focusable="false" focused="false" scrollable="false" long-clickable="false" password="false" selected="false" visible-to-user="true" bounds="[581,1027][678,1060]" drawing-order="1" hint="" display-id="0" />
                                          <node index="1" text="" resource-id="" class="android.widget.TextView" package="com.consumerapp_v1" content-desc="" checkable="false" checked="false" clickable="false" enabled="true" focusable="false" focused="false" scrollable="false" long-clickable="false" password="false" selected="false" visible-to-user="true" bounds="[678,1030][701,1058]" drawing-order="2" hint="" display-id="0" />
                                        </node>
                                      </node>
                                    </node>
                                  </node>
                                </node>
                              </node>
                            </node>
                            <node index="1" text="" resource-id="" class="android.view.ViewGroup" package="com.consumerapp_v1" content-desc="" checkable="false" checked="false" clickable="false" enabled="true" focusable="false" focused="false" scrollable="false" long-clickable="false" password="false" selected="false" visible-to-user="true" bounds="[0,48][768,1184]" drawing-order="1" hint="" display-id="0" />
                          </node>
                        </node>
                      </node>
                    </node>
                  </node>
                </node>
              </node>
            </node>
          </node>
        </node>
      </node>
    </node>
  </node>
  <node index="0" text="" resource-id="" class="android.widget.FrameLayout" package="com.android.systemui" content-desc="" checkable="false" checked="false" clickable="false" enabled="true" focusable="false" focused="false" scrollable="false" long-clickable="false" password="false" selected="false" visible-to-user="true" bounds="[0,0][768,48]" drawing-order="0" hint="" display-id="0">
    <node index="0" text="" resource-id="com.android.systemui:id/status_bar_launch_animation_container" class="android.widget.FrameLayout" package="com.android.systemui" content-desc="" checkable="false" checked="false" clickable="false" enabled="true" focusable="false" focused="false" scrollable="false" long-clickable="false" password="false" selected="false" visible-to-user="true" bounds="[0,0][768,48]" drawing-order="1" hint="" display-id="0" />
    <node index="1" text="" resource-id="com.android.systemui:id/status_bar_container" class="android.widget.FrameLayout" package="com.android.systemui" content-desc="" checkable="false" checked="false" clickable="false" enabled="true" focusable="false" focused="false" scrollable="false" long-clickable="false" password="false" selected="false" visible-to-user="true" bounds="[0,0][768,48]" drawing-order="2" hint="" display-id="0">
      <node index="0" text="" resource-id="com.android.systemui:id/status_bar" class="android.widget.FrameLayout" package="com.android.systemui" content-desc="" checkable="false" checked="false" clickable="false" enabled="true" focusable="false" focused="false" scrollable="false" long-clickable="false" password="false" selected="false" visible-to-user="true" bounds="[0,0][768,48]" drawing-order="1" hint="" display-id="0">
        <node index="0" text="" resource-id="com.android.systemui:id/status_bar_contents" class="android.widget.LinearLayout" package="com.android.systemui" content-desc="" checkable="false" checked="false" clickable="false" enabled="true" focusable="false" focused="false" scrollable="false" long-clickable="false" password="false" selected="false" visible-to-user="true" bounds="[0,0][728,48]" drawing-order="2" hint="" display-id="0">
          <node index="0" text="" resource-id="" class="android.widget.FrameLayout" package="com.android.systemui" content-desc="" checkable="false" checked="false" clickable="false" enabled="true" focusable="false" focused="false" scrollable="false" long-clickable="false" password="false" selected="false" visible-to-user="true" bounds="[16,0][364,48]" drawing-order="1" hint="" display-id="0">
            <node index="0" text="" resource-id="com.android.systemui:id/status_bar_left_side" class="android.widget.LinearLayout" package="com.android.systemui" content-desc="" checkable="false" checked="false" clickable="false" enabled="true" focusable="false" focused="false" scrollable="false" long-clickable="false" password="false" selected="false" visible-to-user="true" bounds="[16,0][364,48]" drawing-order="2" hint="" display-id="0">
              <node index="0" text="5:37" resource-id="com.android.systemui:id/clock" class="android.widget.TextView" package="com.android.systemui" content-desc="5:37 PM" checkable="false" checked="false" clickable="false" enabled="true" focusable="false" focused="false" scrollable="false" long-clickable="false" password="false" selected="false" visible-to-user="true" bounds="[16,0][85,48]" drawing-order="2" hint="" display-id="0" />
              <node index="1" text="" resource-id="com.android.systemui:id/notification_icon_area" class="android.widget.FrameLayout" package="com.android.systemui" content-desc="" checkable="false" checked="false" clickable="false" enabled="true" focusable="false" focused="false" scrollable="false" long-clickable="false" password="false" selected="false" visible-to-user="true" bounds="[85,0][364,48]" drawing-order="4" hint="" display-id="0">
                <node index="0" text="" resource-id="com.android.systemui:id/notification_icon_area_inner" class="android.widget.LinearLayout" package="com.android.systemui" content-desc="" checkable="false" checked="false" clickable="false" enabled="true" focusable="false" focused="false" scrollable="false" long-clickable="false" password="false" selected="false" visible-to-user="true" bounds="[85,0][364,48]" drawing-order="1" hint="" display-id="0">
                  <node index="0" text="" resource-id="com.android.systemui:id/notificationIcons" class="android.widget.FrameLayout" package="com.android.systemui" content-desc="" checkable="false" checked="false" clickable="false" enabled="true" focusable="false" focused="false" scrollable="false" long-clickable="false" password="false" selected="false" visible-to-user="true" bounds="[85,0][364,48]" drawing-order="1" hint="" display-id="0">
                    <node index="0" text="" resource-id="" class="android.widget.ImageView" package="com.android.systemui" content-desc="Gmail notification: 50 new messages" checkable="false" checked="false" clickable="false" enabled="true" focusable="false" focused="false" scrollable="false" long-clickable="false" password="false" selected="false" visible-to-user="true" bounds="[85,0][129,48]" drawing-order="1" hint="" display-id="0" />
                    <node index="1" text="" resource-id="" class="android.widget.ImageView" package="com.android.systemui" content-desc="ATX notification: UIAutomator" checkable="false" checked="false" clickable="false" enabled="true" focusable="false" focused="false" scrollable="false" long-clickable="false" password="false" selected="false" visible-to-user="true" bounds="[129,0][173,48]" drawing-order="2" hint="" display-id="0" />
                    <node index="2" text="" resource-id="" class="android.widget.ImageView" package="com.android.systemui" content-desc="Digital Wellbeing notification: Need time to focus?" checkable="false" checked="false" clickable="false" enabled="true" focusable="false" focused="false" scrollable="false" long-clickable="false" password="false" selected="false" visible-to-user="true" bounds="[173,0][217,48]" drawing-order="3" hint="" display-id="0" />
                    <node index="3" text="" resource-id="" class="android.widget.ImageView" package="com.android.systemui" content-desc="Google notification: KHOU" checkable="false" checked="false" clickable="false" enabled="true" focusable="false" focused="false" scrollable="false" long-clickable="false" password="false" selected="false" visible-to-user="true" bounds="[217,0][261,48]" drawing-order="4" hint="" display-id="0" />
                  </node>
                </node>
              </node>
            </node>
          </node>
          <node index="1" text="" resource-id="com.android.systemui:id/system_icon_area" class="android.widget.LinearLayout" package="com.android.systemui" content-desc="" checkable="false" checked="false" clickable="false" enabled="true" focusable="false" focused="false" scrollable="false" long-clickable="false" password="false" selected="false" visible-to-user="true" bounds="[364,0][712,48]" drawing-order="4" hint="" display-id="0">
            <node index="0" text="" resource-id="com.android.systemui:id/system_icons" class="android.widget.LinearLayout" package="com.android.systemui" content-desc="" checkable="false" checked="false" clickable="false" enabled="true" focusable="false" focused="false" scrollable="false" long-clickable="false" password="false" selected="false" visible-to-user="true" bounds="[364,0][712,48]" drawing-order="1" hint="" display-id="0">
              <node index="0" text="" resource-id="com.android.systemui:id/statusIcons" class="android.widget.LinearLayout" package="com.android.systemui" content-desc="" checkable="false" checked="false" clickable="false" enabled="true" focusable="false" focused="false" scrollable="false" long-clickable="false" password="false" selected="false" visible-to-user="true" bounds="[364,0][696,48]" drawing-order="1" hint="" display-id="0">
                <node index="0" text="" resource-id="com.android.systemui:id/wifi_combo" class="android.widget.FrameLayout" package="com.android.systemui" content-desc="Wifi signal full." checkable="false" checked="false" clickable="false" enabled="true" focusable="false" focused="false" scrollable="false" long-clickable="false" password="false" selected="false" visible-to-user="true" bounds="[605,2][648,46]" drawing-order="15" hint="" display-id="0">
                  <node index="0" text="" resource-id="com.android.systemui:id/wifi_group" class="android.widget.LinearLayout" package="com.android.systemui" content-desc="" checkable="false" checked="false" clickable="false" enabled="true" focusable="false" focused="false" scrollable="false" long-clickable="false" password="false" selected="false" visible-to-user="true" bounds="[610,2][648,46]" drawing-order="1" hint="" display-id="0">
                    <node index="0" text="" resource-id="com.android.systemui:id/wifi_combo" class="android.widget.FrameLayout" package="com.android.systemui" content-desc="" checkable="false" checked="false" clickable="false" enabled="true" focusable="false" focused="false" scrollable="false" long-clickable="false" password="false" selected="false" visible-to-user="true" bounds="[610,9][640,39]" drawing-order="2" hint="" display-id="0">
                      <node index="0" text="" resource-id="com.android.systemui:id/wifi_signal" class="android.widget.ImageView" package="com.android.systemui" content-desc="" checkable="false" checked="false" clickable="false" enabled="true" focusable="false" focused="false" scrollable="false" long-clickable="false" password="false" selected="false" visible-to-user="true" bounds="[610,9][640,39]" drawing-order="1" hint="" display-id="0" />
                    </node>
                    <node index="1" text="" resource-id="com.android.systemui:id/wifi_airplane_spacer" class="android.view.View" package="com.android.systemui" content-desc="" checkable="false" checked="false" clickable="false" enabled="true" focusable="false" focused="false" scrollable="false" long-clickable="false" password="false" selected="false" visible-to-user="true" bounds="[640,20][648,28]" drawing-order="5" hint="" display-id="0" />
                  </node>
                </node>
                <node index="1" text="" resource-id="" class="android.widget.ImageView" package="com.android.systemui" content-desc="Airplane mode." checkable="false" checked="false" clickable="false" enabled="true" focusable="false" focused="false" scrollable="false" long-clickable="false" password="false" selected="false" visible-to-user="true" bounds="[648,2][684,46]" drawing-order="17" hint="" display-id="0" />
              </node>
              <node index="1" text="" resource-id="com.android.systemui:id/battery" class="android.widget.LinearLayout" package="com.android.systemui" content-desc="Battery 100 percent." checkable="false" checked="false" clickable="false" enabled="true" focusable="false" focused="false" scrollable="false" long-clickable="false" password="false" selected="false" visible-to-user="true" bounds="[696,0][712,48]" drawing-order="2" hint="" display-id="0">
                <node index="0" text="" resource-id="" class="android.widget.ImageView" package="com.android.systemui" content-desc="" checkable="false" checked="false" clickable="false" enabled="true" focusable="false" focused="false" scrollable="false" long-clickable="false" password="false" selected="false" visible-to-user="true" bounds="[696,11][712,37]" drawing-order="1" hint="" display-id="0" />
              </node>
            </node>
          </node>
        </node>
      </node>
    </node>
  </node>
  <node index="0" text="" resource-id="com.android.systemui:id/navigation_bar_frame" class="android.widget.FrameLayout" package="com.android.systemui" content-desc="" checkable="false" checked="false" clickable="false" enabled="true" focusable="false" focused="false" scrollable="false" long-clickable="false" password="false" selected="false" visible-to-user="true" bounds="[0,1184][768,1280]" drawing-order="0" hint="" display-id="0">
    <node index="0" text="" resource-id="com.android.systemui:id/navigation_bar_view" class="android.widget.FrameLayout" package="com.android.systemui" content-desc="" checkable="false" checked="false" clickable="false" enabled="true" focusable="false" focused="false" scrollable="false" long-clickable="false" password="false" selected="false" visible-to-user="true" bounds="[0,1184][768,1280]" drawing-order="1" hint="" display-id="0">
      <node index="0" text="" resource-id="com.android.systemui:id/navigation_inflater" class="android.widget.FrameLayout" package="com.android.systemui" content-desc="" checkable="false" checked="false" clickable="false" enabled="true" focusable="false" focused="false" scrollable="false" long-clickable="false" password="false" selected="false" visible-to-user="true" bounds="[0,1184][768,1280]" drawing-order="1" hint="" display-id="0">
        <node index="0" text="" resource-id="com.android.systemui:id/horizontal" class="android.widget.FrameLayout" package="com.android.systemui" content-desc="" checkable="false" checked="false" clickable="false" enabled="true" focusable="false" focused="false" scrollable="false" long-clickable="false" password="false" selected="false" visible-to-user="true" bounds="[0,1184][768,1280]" drawing-order="1" hint="" display-id="0">
          <node index="0" text="" resource-id="com.android.systemui:id/nav_buttons" class="android.widget.FrameLayout" package="com.android.systemui" content-desc="" checkable="false" checked="false" clickable="false" enabled="true" focusable="false" focused="false" scrollable="false" long-clickable="false" password="false" selected="false" visible-to-user="true" bounds="[16,1184][752,1280]" drawing-order="1" hint="" display-id="0">
            <node index="0" text="" resource-id="com.android.systemui:id/ends_group" class="android.widget.LinearLayout" package="com.android.systemui" content-desc="" checkable="false" checked="false" clickable="false" enabled="true" focusable="false" focused="false" scrollable="false" long-clickable="false" password="false" selected="false" visible-to-user="true" bounds="[16,1184][752,1280]" drawing-order="1" hint="" display-id="0">
              <node index="0" text="" resource-id="" class="android.widget.RelativeLayout" package="com.android.systemui" content-desc="" checkable="false" checked="false" clickable="false" enabled="true" focusable="false" focused="false" scrollable="false" long-clickable="false" password="false" selected="false" visible-to-user="true" bounds="[16,1184][89,1280]" drawing-order="1" hint="" display-id="0" />
              <node index="1" text="" resource-id="" class="android.widget.RelativeLayout" package="com.android.systemui" content-desc="" checkable="false" checked="false" clickable="false" enabled="true" focusable="false" focused="false" scrollable="false" long-clickable="false" password="false" selected="false" visible-to-user="true" bounds="[89,1184][236,1280]" drawing-order="2" hint="" display-id="0">
                <node index="0" text="" resource-id="com.android.systemui:id/back" class="android.widget.ImageView" package="com.android.systemui" content-desc="Back" checkable="false" checked="false" clickable="true" enabled="true" focusable="true" focused="false" scrollable="false" long-clickable="false" password="false" selected="false" visible-to-user="true" bounds="[89,1184][236,1280]" drawing-order="1" hint="" display-id="0" />
              </node>
              <node index="2" text="" resource-id="" class="android.widget.RelativeLayout" package="com.android.systemui" content-desc="" checkable="false" checked="false" clickable="false" enabled="true" focusable="false" focused="false" scrollable="false" long-clickable="false" password="false" selected="false" visible-to-user="true" bounds="[530,1184][678,1280]" drawing-order="4" hint="" display-id="0">
                <node index="0" text="" resource-id="com.android.systemui:id/recent_apps" class="android.widget.ImageView" package="com.android.systemui" content-desc="Overview" checkable="false" checked="false" clickable="true" enabled="true" focusable="true" focused="false" scrollable="false" long-clickable="false" password="false" selected="false" visible-to-user="true" bounds="[530,1184][678,1280]" drawing-order="1" hint="" display-id="0" />
              </node>
              <node index="3" text="" resource-id="" class="android.widget.RelativeLayout" package="com.android.systemui" content-desc="" checkable="false" checked="false" clickable="false" enabled="true" focusable="false" focused="false" scrollable="false" long-clickable="false" password="false" selected="false" visible-to-user="true" bounds="[678,1184][752,1280]" drawing-order="5" hint="" display-id="0" />
            </node>
            <node index="1" text="" resource-id="com.android.systemui:id/center_group" class="android.widget.LinearLayout" package="com.android.systemui" content-desc="" checkable="false" checked="false" clickable="false" enabled="true" focusable="false" focused="false" scrollable="false" long-clickable="false" password="false" selected="false" visible-to-user="true" bounds="[304,1184][464,1280]" drawing-order="2" hint="" display-id="0">
              <node index="0" text="" resource-id="com.android.systemui:id/home" class="android.widget.FrameLayout" package="com.android.systemui" content-desc="" checkable="false" checked="false" clickable="true" enabled="true" focusable="true" focused="false" scrollable="false" long-clickable="true" password="false" selected="false" visible-to-user="true" bounds="[304,1184][464,1280]" drawing-order="1" hint="" display-id="0">
                <node index="0" text="" resource-id="com.android.systemui:id/home_button" class="android.widget.ImageView" package="com.android.systemui" content-desc="Home" checkable="false" checked="false" clickable="true" enabled="true" focusable="true" focused="false" scrollable="false" long-clickable="true" password="false" selected="false" visible-to-user="true" bounds="[304,1184][464,1280]" drawing-order="5" hint="" display-id="0" />
                <node index="1" text="" resource-id="" class="android.widget.RelativeLayout" package="com.android.systemui" content-desc="" checkable="false" checked="false" clickable="false" enabled="true" focusable="false" focused="false" scrollable="false" long-clickable="false" password="false" selected="false" visible-to-user="true" bounds="[304,1184][464,1280]" drawing-order="1" hint="" display-id="0" />
                <node index="2" text="" resource-id="com.android.systemui:id/white_cutout" class="android.widget.ImageView" package="com.android.systemui" content-desc="" checkable="false" checked="false" clickable="false" enabled="true" focusable="false" focused="false" scrollable="false" long-clickable="false" password="false" selected="false" visible-to-user="true" bounds="[352,1200][416,1264]" drawing-order="3" hint="" display-id="0" />
                <node index="3" text="" resource-id="com.android.systemui:id/white" class="android.widget.ImageView" package="com.android.systemui" content-desc="" checkable="false" checked="false" clickable="false" enabled="true" focusable="false" focused="false" scrollable="false" long-clickable="false" password="false" selected="false" visible-to-user="true" bounds="[352,1200][416,1264]" drawing-order="4" hint="" display-id="0" />
              </node>
            </node>
          </node>
        </node>
      </node>
    </node>
  </node>
</hierarchy>