<?xml version='1.0' encoding='UTF-8' standalone='yes' ?>
<hierarchy rotation="0">
  <node index="0" text="" resource-id="" class="android.widget.FrameLayout" package="com.google.android.apps.maps" content-desc="" checkable="false" checked="false" clickable="false" enabled="true" focusable="false" focused="false" scrollable="false" long-clickable="false" password="false" selected="false" visible-to-user="true" bounds="[0,0][768,1280]" drawing-order="0" hint="" display-id="0">
    <node index="0" text="" resource-id="" class="android.widget.LinearLayout" package="com.google.android.apps.maps" content-desc="" checkable="false" checked="false" clickable="false" enabled="true" focusable="false" focused="false" scrollable="false" long-clickable="false" password="false" selected="false" visible-to-user="true" bounds="[0,0][768,1184]" drawing-order="1" hint="" display-id="0">
      <node index="0" text="" resource-id="" class="android.widget.FrameLayout" package="com.google.android.apps.maps" content-desc="" checkable="false" checked="false" clickable="false" enabled="true" focusable="false" focused="false" scrollable="false" long-clickable="false" password="false" selected="false" visible-to-user="true" bounds="[0,0][768,1184]" drawing-order="2" hint="" display-id="0">
        <node index="0" text="" resource-id="com.google.android.apps.maps:id/action_bar_root" class="android.widget.LinearLayout" package="com.google.android.apps.maps" content-desc="" checkable="false" checked="false" clickable="false" enabled="true" focusable="false" focused="false" scrollable="false" long-clickable="false" password="false" selected="false" visible-to-user="true" bounds="[0,0][768,1184]" drawing-order="1" hint="" display-id="0">
          <node index="0" text="" resource-id="android:id/content" class="android.widget.FrameLayout" package="com.google.android.apps.maps" content-desc="" checkable="false" checked="false" clickable="false" enabled="true" focusable="false" focused="false" scrollable="false" long-clickable="false" password="false" selected="false" visible-to-user="true" bounds="[0,0][768,1184]" drawing-order="2" hint="" display-id="0">
            <node index="0" text="" resource-id="" class="android.widget.FrameLayout" package="com.google.android.apps.maps" content-desc="" checkable="false" checked="false" clickable="false" enabled="true" focusable="false" focused="false" scrollable="false" long-clickable="false" password="false" selected="false" visible-to-user="true" bounds="[0,0][768,1184]" drawing-order="1" hint="" display-id="0">
              <node index="0" text="" resource-id="" class="android.widget.LinearLayout" package="com.google.android.apps.maps" content-desc="" checkable="false" checked="false" clickable="false" enabled="true" focusable="false" focused="false" scrollable="false" long-clickable="false" password="false" selected="false" visible-to-user="true" bounds="[0,0][768,1184]" drawing-order="1" hint="" display-id="0">
                <node index="0" text="" resource-id="com.google.android.apps.maps:id/mainmap_container" class="android.view.ViewGroup" package="com.google.android.apps.maps" content-desc="" checkable="false" checked="false" clickable="false" enabled="true" focusable="false" focused="false" scrollable="false" long-clickable="false" password="false" selected="false" visible-to-user="true" bounds="[0,0][768,1184]" drawing-order="2" hint="" display-id="0">
                  <node index="3" text="" resource-id="com.google.android.apps.maps:id/map_frame" class="android.widget.FrameLayout" package="com.google.android.apps.maps" content-desc="" checkable="false" checked="false" clickable="false" enabled="true" focusable="false" focused="false" scrollable="false" long-clickable="false" password="false" selected="false" visible-to-user="true" bounds="[0,0][768,1184]" drawing-order="1" hint="" display-id="0">
                    <node NAF="true" index="0" text="" resource-id="" class="android.view.View" package="com.google.android.apps.maps" content-desc="" checkable="false" checked="false" clickable="true" enabled="true" focusable="true" focused="false" scrollable="false" long-clickable="false" password="false" selected="false" visible-to-user="true" bounds="[0,0][768,1184]" drawing-order="1" hint="" display-id="0" />
                  </node>
                  <node index="4" text="" resource-id="com.google.android.apps.maps:id/fullscreens_group" class="android.widget.FrameLayout" package="com.google.android.apps.maps" content-desc="" checkable="false" checked="false" clickable="false" enabled="true" focusable="false" focused="false" scrollable="false" long-clickable="false" password="false" selected="false" visible-to-user="true" bounds="[0,0][768,1184]" drawing-order="27" hint="" display-id="0" />
                  <node index="5" text="" resource-id="com.google.android.apps.maps:id/search_omnibox_container" class="android.widget.FrameLayout" package="com.google.android.apps.maps" content-desc="" checkable="false" checked="false" clickable="false" enabled="true" focusable="true" focused="true" scrollable="false" long-clickable="false" password="false" selected="false" visible-to-user="true" bounds="[0,0][768,286]" drawing-order="24" hint="" display-id="0">
                    <node index="0" text="" resource-id="com.google.android.apps.maps:id/search_list_omnibox_layout" class="android.widget.LinearLayout" package="com.google.android.apps.maps" content-desc="" checkable="false" checked="false" clickable="false" enabled="true" focusable="false" focused="false" scrollable="false" long-clickable="false" password="false" selected="false" visible-to-user="true" bounds="[0,0][768,286]" drawing-order="1" hint="" display-id="0">
                      <node index="0" text="" resource-id="" class="android.widget.FrameLayout" package="com.google.android.apps.maps" content-desc="" checkable="false" checked="false" clickable="false" enabled="true" focusable="false" focused="false" scrollable="false" long-clickable="false" password="false" selected="false" visible-to-user="true" bounds="[0,0][768,184]" drawing-order="2" hint="" display-id="0">
                        <node index="0" text="" resource-id="" class="android.widget.FrameLayout" package="com.google.android.apps.maps" content-desc="" checkable="false" checked="false" clickable="false" enabled="true" focusable="false" focused="false" scrollable="false" long-clickable="false" password="false" selected="false" visible-to-user="true" bounds="[0,0][768,184]" drawing-order="1" hint="" display-id="0" />
                        <node index="1" text="" resource-id="" class="android.widget.LinearLayout" package="com.google.android.apps.maps" content-desc="" checkable="false" checked="false" clickable="false" enabled="true" focusable="false" focused="false" scrollable="false" long-clickable="false" password="false" selected="false" visible-to-user="true" bounds="[0,0][768,184]" drawing-order="2" hint="" display-id="0">
                          <node index="0" text="" resource-id="" class="android.widget.FrameLayout" package="com.google.android.apps.maps" content-desc="" checkable="false" checked="false" clickable="false" enabled="true" focusable="false" focused="false" scrollable="false" long-clickable="false" password="false" selected="false" visible-to-user="true" bounds="[12,46][756,178]" drawing-order="1" hint="" display-id="0">
                            <node index="0" text="" resource-id="" class="android.widget.LinearLayout" package="com.google.android.apps.maps" content-desc="" checkable="false" checked="false" clickable="false" enabled="true" focusable="false" focused="false" scrollable="false" long-clickable="false" password="false" selected="false" visible-to-user="true" bounds="[24,64][744,160]" drawing-order="1" hint="" display-id="0">
                              <node index="0" text="" resource-id="" class="android.widget.FrameLayout" package="com.google.android.apps.maps" content-desc="" checkable="false" checked="false" clickable="false" enabled="true" focusable="false" focused="false" scrollable="false" long-clickable="false" password="false" selected="false" visible-to-user="true" bounds="[24,64][744,160]" drawing-order="1" hint="" display-id="0">
                                <node index="0" text="" resource-id="" class="android.widget.LinearLayout" package="com.google.android.apps.maps" content-desc="" checkable="false" checked="false" clickable="false" enabled="true" focusable="false" focused="false" scrollable="false" long-clickable="false" password="false" selected="false" visible-to-user="true" bounds="[24,64][744,160]" drawing-order="1" hint="" display-id="0">
                                  <node index="0" text="" resource-id="" class="android.widget.FrameLayout" package="com.google.android.apps.maps" content-desc="" checkable="false" checked="false" clickable="false" enabled="true" focusable="false" focused="false" scrollable="false" long-clickable="false" password="false" selected="false" visible-to-user="true" bounds="[24,64][120,160]" drawing-order="1" hint="" display-id="0">
                                    <node index="0" text="" resource-id="com.google.android.apps.maps:id/search_omnibox_menu_button" class="android.widget.Button" package="com.google.android.apps.maps" content-desc="Back" checkable="false" checked="false" clickable="true" enabled="true" focusable="true" focused="false" scrollable="false" long-clickable="false" password="false" selected="false" visible-to-user="true" bounds="[24,64][120,160]" drawing-order="1" hint="" display-id="0">
                                      <node index="0" text="" resource-id="" class="android.widget.ImageView" package="com.google.android.apps.maps" content-desc="" checkable="false" checked="false" clickable="false" enabled="true" focusable="false" focused="false" scrollable="false" long-clickable="false" password="false" selected="false" visible-to-user="true" bounds="[48,88][96,136]" drawing-order="1" hint="" display-id="0" />
                                    </node>
                                  </node>
                                  <node index="1" text="" resource-id="com.google.android.apps.maps:id/search_omnibox_text_box" class="android.widget.EditText" package="com.google.android.apps.maps" content-desc="" checkable="false" checked="false" clickable="true" enabled="true" focusable="true" focused="false" scrollable="false" long-clickable="false" password="false" selected="false" visible-to-user="true" bounds="[120,64][552,160]" drawing-order="2" hint="" display-id="0">
                                    <node index="0" text="restaurants near me" resource-id="" class="android.widget.TextView" package="com.google.android.apps.maps" content-desc="" checkable="false" checked="false" clickable="false" enabled="true" focusable="false" focused="false" scrollable="false" long-clickable="false" password="false" selected="false" visible-to-user="true" bounds="[120,64][552,160]" drawing-order="2" hint="" display-id="0" />
                                  </node>
                                  <node index="2" text="" resource-id="com.google.android.apps.maps:id/search_omnibox_text_clear" class="android.widget.Button" package="com.google.android.apps.maps" content-desc="" checkable="false" checked="false" clickable="true" enabled="true" focusable="true" focused="false" scrollable="false" long-clickable="false" password="false" selected="false" visible-to-user="true" bounds="[552,64][648,160]" drawing-order="4" hint="" display-id="0">
                                    <node index="0" text="" resource-id="" class="android.widget.ImageView" package="com.google.android.apps.maps" content-desc="Clear" checkable="false" checked="false" clickable="false" enabled="true" focusable="false" focused="false" scrollable="false" long-clickable="false" password="false" selected="false" visible-to-user="true" bounds="[576,88][624,136]" drawing-order="1" hint="" display-id="0" />
                                  </node>
                                  <node index="3" text="" resource-id="" class="android.widget.ImageButton" package="com.google.android.apps.maps" content-desc="Voice search" checkable="false" checked="false" clickable="true" enabled="true" focusable="true" focused="false" scrollable="false" long-clickable="false" password="false" selected="false" visible-to-user="true" bounds="[648,64][744,160]" drawing-order="5" hint="" display-id="0" />
                                </node>
                              </node>
                            </node>
                          </node>
                        </node>
                      </node>
                      <node index="1" text="" resource-id="" class="android.widget.LinearLayout" package="com.google.android.apps.maps" content-desc="" checkable="false" checked="false" clickable="false" enabled="true" focusable="false" focused="false" scrollable="false" long-clickable="false" password="false" selected="false" visible-to-user="true" bounds="[0,184][768,286]" drawing-order="3" hint="" display-id="0">
                        <node index="0" text="" resource-id="" class="android.widget.HorizontalScrollView" package="com.google.android.apps.maps" content-desc="" checkable="false" checked="false" clickable="false" enabled="true" focusable="true" focused="false" scrollable="true" long-clickable="false" password="false" selected="false" visible-to-user="true" bounds="[0,184][768,280]" drawing-order="1" hint="" display-id="0">
                          <node index="0" text="" resource-id="" class="android.widget.LinearLayout" package="com.google.android.apps.maps" content-desc="" checkable="false" checked="false" clickable="false" enabled="true" focusable="false" focused="false" scrollable="false" long-clickable="false" password="false" selected="false" visible-to-user="true" bounds="[0,184][768,280]" drawing-order="1" hint="" display-id="0">
                            <node index="0" text="" resource-id="" class="android.widget.FrameLayout" package="com.google.android.apps.maps" content-desc="More filters" checkable="false" checked="false" clickable="true" enabled="true" focusable="true" focused="false" scrollable="false" long-clickable="false" password="false" selected="false" visible-to-user="true" bounds="[0,184][96,280]" drawing-order="1" hint="" display-id="0">
                              <node index="0" text="" resource-id="" class="android.widget.CompoundButton" package="com.google.android.apps.maps" content-desc="" checkable="true" checked="false" clickable="false" enabled="true" focusable="true" focused="false" scrollable="false" long-clickable="false" password="false" selected="false" visible-to-user="true" bounds="[16,192][80,256]" drawing-order="1" hint="" display-id="0" />
                            </node>
                            <node index="1" text="" resource-id="" class="android.widget.LinearLayout" package="com.google.android.apps.maps" content-desc="" checkable="false" checked="false" clickable="false" enabled="true" focusable="false" focused="false" scrollable="false" long-clickable="false" password="false" selected="false" visible-to-user="true" bounds="[96,184][768,280]" drawing-order="3" hint="" display-id="0">
                              <node index="0" text="" resource-id="" class="android.widget.FrameLayout" package="com.google.android.apps.maps" content-desc="Tap to filter by Open now. Not Selected" checkable="false" checked="false" clickable="true" enabled="true" focusable="true" focused="false" scrollable="false" long-clickable="false" password="false" selected="false" visible-to-user="true" bounds="[102,184][278,280]" drawing-order="1" hint="" display-id="0">
                                <node index="0" text="Open now" resource-id="" class="android.view.View" package="com.google.android.apps.maps" content-desc="" checkable="false" checked="false" clickable="false" enabled="true" focusable="false" focused="false" scrollable="false" long-clickable="false" password="false" selected="false" visible-to-user="true" bounds="[102,192][278,256]" drawing-order="1" hint="" display-id="0" />
                              </node>
                              <node index="1" text="" resource-id="" class="android.widget.FrameLayout" package="com.google.android.apps.maps" content-desc="Tap to filter by Cuisine. Not Selected" checkable="false" checked="false" clickable="true" enabled="true" focusable="true" focused="false" scrollable="false" long-clickable="false" password="false" selected="false" visible-to-user="true" bounds="[290,184][460,280]" drawing-order="2" hint="" display-id="0">
                                <node index="0" text="Cuisine" resource-id="" class="android.view.View" package="com.google.android.apps.maps" content-desc="" checkable="false" checked="false" clickable="false" enabled="true" focusable="false" focused="false" scrollable="false" long-clickable="false" password="false" selected="false" visible-to-user="true" bounds="[290,192][460,256]" drawing-order="1" hint="" display-id="0">
                                  <node index="1" text="" resource-id="" class="android.view.View" package="com.google.android.apps.maps" content-desc="Remove Cuisine" checkable="false" checked="false" clickable="false" enabled="true" focusable="true" focused="false" scrollable="false" long-clickable="false" password="false" selected="false" visible-to-user="true" bounds="[408,192][460,256]" drawing-order="0" hint="" display-id="0" />
                                </node>
                              </node>
                              <node index="2" text="" resource-id="" class="android.widget.FrameLayout" package="com.google.android.apps.maps" content-desc="Tap to filter by Price. Not Selected" checkable="false" checked="false" clickable="true" enabled="true" focusable="true" focused="false" scrollable="false" long-clickable="false" password="false" selected="false" visible-to-user="true" bounds="[472,184][614,280]" drawing-order="3" hint="" display-id="0">
                                <node index="0" text="Price" resource-id="" class="android.view.View" package="com.google.android.apps.maps" content-desc="" checkable="false" checked="false" clickable="false" enabled="true" focusable="false" focused="false" scrollable="false" long-clickable="false" password="false" selected="false" visible-to-user="true" bounds="[472,192][614,256]" drawing-order="1" hint="" display-id="0">
                                  <node index="1" text="" resource-id="" class="android.view.View" package="com.google.android.apps.maps" content-desc="Remove Price" checkable="false" checked="false" clickable="false" enabled="true" focusable="true" focused="false" scrollable="false" long-clickable="false" password="false" selected="false" visible-to-user="true" bounds="[562,192][614,256]" drawing-order="0" hint="" display-id="0" />
                                </node>
                              </node>
                              <node index="3" text="" resource-id="" class="android.widget.FrameLayout" package="com.google.android.apps.maps" content-desc="Tap to filter by Top rated. Not Selected" checkable="false" checked="false" clickable="true" enabled="true" focusable="true" focused="false" scrollable="false" long-clickable="false" password="false" selected="false" visible-to-user="true" bounds="[626,184][768,280]" drawing-order="4" hint="" display-id="0">
                                <node index="0" text="Top rated" resource-id="" class="android.view.View" package="com.google.android.apps.maps" content-desc="" checkable="false" checked="false" clickable="false" enabled="true" focusable="false" focused="false" scrollable="false" long-clickable="false" password="false" selected="false" visible-to-user="true" bounds="[626,192][768,256]" drawing-order="1" hint="" display-id="0" />
                              </node>
                            </node>
                          </node>
                        </node>
                        <node index="1" text="" resource-id="" class="android.widget.FrameLayout" package="com.google.android.apps.maps" content-desc="" checkable="false" checked="false" clickable="false" enabled="true" focusable="false" focused="false" scrollable="false" long-clickable="false" password="false" selected="false" visible-to-user="true" bounds="[0,280][768,286]" drawing-order="3" hint="" display-id="0">
                          <node index="0" text="" resource-id="" class="android.view.View" package="com.google.android.apps.maps" content-desc="" checkable="false" checked="false" clickable="false" enabled="true" focusable="false" focused="false" scrollable="false" long-clickable="false" password="false" selected="false" visible-to-user="true" bounds="[0,280][768,286]" drawing-order="1" hint="" display-id="0" />
                        </node>
                      </node>
                    </node>
                  </node>
                  <node index="6" text="" resource-id="com.google.android.apps.maps:id/home_bottom_sheet_container" class="android.widget.FrameLayout" package="com.google.android.apps.maps" content-desc="" checkable="false" checked="false" clickable="false" enabled="true" focusable="false" focused="false" scrollable="false" long-clickable="false" password="false" selected="false" visible-to-user="true" bounds="[0,280][768,1184]" drawing-order="21" hint="" display-id="0" />
                  <node index="7" text="" resource-id="com.google.android.apps.maps:id/custom_slider_container" class="android.widget.FrameLayout" package="com.google.android.apps.maps" content-desc="" checkable="false" checked="false" clickable="false" enabled="true" focusable="false" focused="false" scrollable="false" long-clickable="false" password="false" selected="false" visible-to-user="true" bounds="[0,280][768,1184]" drawing-order="26" hint="" display-id="0">
                    <node index="0" text="" resource-id="" class="android.widget.ScrollView" package="com.google.android.apps.maps" content-desc="" checkable="false" checked="false" clickable="false" enabled="true" focusable="false" focused="false" scrollable="true" long-clickable="false" password="false" selected="false" visible-to-user="true" bounds="[0,280][768,1184]" drawing-order="1" hint="" display-id="0">
                      <node index="0" text="" resource-id="com.google.android.apps.maps:id/search_list_layout" class="android.support.v7.widget.RecyclerView" package="com.google.android.apps.maps" content-desc="" checkable="false" checked="false" clickable="false" enabled="true" focusable="true" focused="false" scrollable="true" long-clickable="false" password="false" selected="false" visible-to-user="true" bounds="[0,506][768,1184]" drawing-order="1" hint="" display-id="0">
                        <node index="0" text="" resource-id="" class="android.widget.ImageView" package="com.google.android.apps.maps" content-desc="" checkable="false" checked="false" clickable="false" enabled="true" focusable="false" focused="false" scrollable="false" long-clickable="false" password="false" selected="false" visible-to-user="true" bounds="[0,506][768,530]" drawing-order="1" hint="" display-id="0" />
                        <node index="1" text="" resource-id="" class="android.widget.LinearLayout" package="com.google.android.apps.maps" content-desc="" checkable="false" checked="false" clickable="false" enabled="true" focusable="false" focused="false" scrollable="false" long-clickable="false" password="false" selected="false" visible-to-user="true" bounds="[0,530][768,818]" drawing-order="2" hint="" display-id="0">
                          <node index="0" text="" resource-id="" class="android.widget.LinearLayout" package="com.google.android.apps.maps" content-desc="" checkable="false" checked="false" clickable="false" enabled="true" focusable="false" focused="false" scrollable="false" long-clickable="false" password="false" selected="false" visible-to-user="true" bounds="[0,530][768,798]" drawing-order="1" hint="" display-id="0">
                            <node index="0" text="" resource-id="com.google.android.apps.maps:id/recycler_view" class="android.support.v7.widget.RecyclerView" package="com.google.android.apps.maps" content-desc="" checkable="false" checked="false" clickable="false" enabled="true" focusable="true" focused="false" scrollable="true" long-clickable="false" password="false" selected="false" visible-to-user="true" bounds="[0,546][768,782]" drawing-order="2" hint="" display-id="0">
                              <node index="0" text="" resource-id="" class="android.widget.FrameLayout" package="com.google.android.apps.maps" content-desc="" checkable="false" checked="false" clickable="true" enabled="true" focusable="true" focused="false" scrollable="false" long-clickable="false" password="false" selected="false" visible-to-user="true" bounds="[36,546][272,782]" drawing-order="1" hint="" display-id="0">
                                <node index="0" text="" resource-id="" class="android.widget.FrameLayout" package="com.google.android.apps.maps" content-desc="" checkable="false" checked="false" clickable="false" enabled="true" focusable="false" focused="false" scrollable="false" long-clickable="false" password="false" selected="false" visible-to-user="true" bounds="[40,552][268,776]" drawing-order="1" hint="" display-id="0">
                                  <node index="0" text="" resource-id="" class="android.widget.ImageView" package="com.google.android.apps.maps" content-desc="" checkable="false" checked="false" clickable="false" enabled="true" focusable="false" focused="false" scrollable="false" long-clickable="false" password="false" selected="false" visible-to-user="true" bounds="[40,552][268,776]" drawing-order="1" hint="" display-id="0" />
                                </node>
                                <node index="1" text="" resource-id="" class="android.view.View" package="com.google.android.apps.maps" content-desc="" checkable="false" checked="false" clickable="false" enabled="true" focusable="false" focused="false" scrollable="false" long-clickable="false" password="false" selected="false" visible-to-user="true" bounds="[40,552][268,776]" drawing-order="2" hint="" display-id="0" />
                                <node index="2" text="" resource-id="" class="android.widget.LinearLayout" package="com.google.android.apps.maps" content-desc="" checkable="false" checked="false" clickable="false" enabled="true" focusable="false" focused="false" scrollable="false" long-clickable="false" password="false" selected="false" visible-to-user="true" bounds="[40,688][268,776]" drawing-order="3" hint="" display-id="0">
                                  <node index="0" text="American" resource-id="" class="android.widget.TextView" package="com.google.android.apps.maps" content-desc="" checkable="false" checked="false" clickable="false" enabled="true" focusable="false" focused="false" scrollable="false" long-clickable="false" password="false" selected="false" visible-to-user="true" bounds="[64,712][244,752]" drawing-order="1" hint="" display-id="0" />
                                </node>
                              </node>
                              <node index="1" text="" resource-id="" class="android.widget.FrameLayout" package="com.google.android.apps.maps" content-desc="" checkable="false" checked="false" clickable="true" enabled="true" focusable="true" focused="false" scrollable="false" long-clickable="false" password="false" selected="false" visible-to-user="true" bounds="[280,546][516,782]" drawing-order="2" hint="" display-id="0">
                                <node index="0" text="" resource-id="" class="android.widget.FrameLayout" package="com.google.android.apps.maps" content-desc="" checkable="false" checked="false" clickable="false" enabled="true" focusable="false" focused="false" scrollable="false" long-clickable="false" password="false" selected="false" visible-to-user="true" bounds="[284,552][512,776]" drawing-order="1" hint="" display-id="0">
                                  <node index="0" text="" resource-id="" class="android.widget.ImageView" package="com.google.android.apps.maps" content-desc="" checkable="false" checked="false" clickable="false" enabled="true" focusable="false" focused="false" scrollable="false" long-clickable="false" password="false" selected="false" visible-to-user="true" bounds="[284,552][512,776]" drawing-order="1" hint="" display-id="0" />
                                </node>
                                <node index="1" text="" resource-id="" class="android.view.View" package="com.google.android.apps.maps" content-desc="" checkable="false" checked="false" clickable="false" enabled="true" focusable="false" focused="false" scrollable="false" long-clickable="false" password="false" selected="false" visible-to-user="true" bounds="[284,552][512,776]" drawing-order="2" hint="" display-id="0" />
                                <node index="2" text="" resource-id="" class="android.widget.LinearLayout" package="com.google.android.apps.maps" content-desc="" checkable="false" checked="false" clickable="false" enabled="true" focusable="false" focused="false" scrollable="false" long-clickable="false" password="false" selected="false" visible-to-user="true" bounds="[284,688][512,776]" drawing-order="3" hint="" display-id="0">
                                  <node index="0" text="Italian" resource-id="" class="android.widget.TextView" package="com.google.android.apps.maps" content-desc="" checkable="false" checked="false" clickable="false" enabled="true" focusable="false" focused="false" scrollable="false" long-clickable="false" password="false" selected="false" visible-to-user="true" bounds="[308,712][488,752]" drawing-order="1" hint="" display-id="0" />
                                </node>
                              </node>
                              <node index="2" text="" resource-id="" class="android.widget.FrameLayout" package="com.google.android.apps.maps" content-desc="" checkable="false" checked="false" clickable="true" enabled="true" focusable="true" focused="false" scrollable="false" long-clickable="false" password="false" selected="false" visible-to-user="true" bounds="[524,546][760,782]" drawing-order="3" hint="" display-id="0">
                                <node index="0" text="" resource-id="" class="android.widget.FrameLayout" package="com.google.android.apps.maps" content-desc="" checkable="false" checked="false" clickable="false" enabled="true" focusable="false" focused="false" scrollable="false" long-clickable="false" password="false" selected="false" visible-to-user="true" bounds="[528,552][756,776]" drawing-order="1" hint="" display-id="0">
                                  <node index="0" text="" resource-id="" class="android.widget.ImageView" package="com.google.android.apps.maps" content-desc="" checkable="false" checked="false" clickable="false" enabled="true" focusable="false" focused="false" scrollable="false" long-clickable="false" password="false" selected="false" visible-to-user="true" bounds="[528,552][756,776]" drawing-order="1" hint="" display-id="0" />
                                </node>
                                <node index="1" text="" resource-id="" class="android.view.View" package="com.google.android.apps.maps" content-desc="" checkable="false" checked="false" clickable="false" enabled="true" focusable="false" focused="false" scrollable="false" long-clickable="false" password="false" selected="false" visible-to-user="true" bounds="[528,552][756,776]" drawing-order="2" hint="" display-id="0" />
                                <node index="2" text="" resource-id="" class="android.widget.LinearLayout" package="com.google.android.apps.maps" content-desc="" checkable="false" checked="false" clickable="false" enabled="true" focusable="false" focused="false" scrollable="false" long-clickable="false" password="false" selected="false" visible-to-user="true" bounds="[528,688][756,776]" drawing-order="3" hint="" display-id="0">
                                  <node index="0" text="Hamburger" resource-id="" class="android.widget.TextView" package="com.google.android.apps.maps" content-desc="" checkable="false" checked="false" clickable="false" enabled="true" focusable="false" focused="false" scrollable="false" long-clickable="false" password="false" selected="false" visible-to-user="true" bounds="[552,712][732,752]" drawing-order="1" hint="" display-id="0" />
                                </node>
                              </node>
                            </node>
                          </node>
                          <node index="1" text="" resource-id="" class="android.widget.LinearLayout" package="com.google.android.apps.maps" content-desc="" checkable="false" checked="false" clickable="false" enabled="true" focusable="false" focused="false" scrollable="false" long-clickable="false" password="false" selected="false" visible-to-user="true" bounds="[0,798][768,818]" drawing-order="2" hint="" display-id="0">
                            <node index="0" text="" resource-id="" class="android.widget.FrameLayout" package="com.google.android.apps.maps" content-desc="" checkable="false" checked="false" clickable="false" enabled="true" focusable="false" focused="false" scrollable="false" long-clickable="false" password="false" selected="false" visible-to-user="true" bounds="[0,798][768,800]" drawing-order="1" hint="" display-id="0" />
                            <node index="1" text="" resource-id="" class="android.widget.FrameLayout" package="com.google.android.apps.maps" content-desc="" checkable="false" checked="false" clickable="false" enabled="true" focusable="false" focused="false" scrollable="false" long-clickable="false" password="false" selected="false" visible-to-user="true" bounds="[0,816][768,818]" drawing-order="3" hint="" display-id="0" />
                          </node>
                        </node>
                        <node index="2" text="" resource-id="" class="android.widget.LinearLayout" package="com.google.android.apps.maps" content-desc="" checkable="false" checked="false" clickable="false" enabled="true" focusable="false" focused="false" scrollable="false" long-clickable="false" password="false" selected="false" visible-to-user="true" bounds="[0,818][768,1184]" drawing-order="3" hint="" display-id="0">
                          <node index="0" text="" resource-id="" class="android.widget.RelativeLayout" package="com.google.android.apps.maps" content-desc="" checkable="false" checked="false" clickable="true" enabled="true" focusable="true" focused="false" scrollable="false" long-clickable="false" password="false" selected="false" visible-to-user="true" bounds="[0,818][768,1184]" drawing-order="1" hint="" display-id="0">
                            <node index="1" text="" resource-id="" class="android.widget.FrameLayout" package="com.google.android.apps.maps" content-desc="" checkable="false" checked="false" clickable="false" enabled="true" focusable="false" focused="false" scrollable="false" long-clickable="false" password="false" selected="false" visible-to-user="true" bounds="[0,818][768,1102]" drawing-order="2" hint="" display-id="0">
                              <node index="0" text="" resource-id="" class="android.widget.FrameLayout" package="com.google.android.apps.maps" content-desc="" checkable="false" checked="false" clickable="false" enabled="true" focusable="false" focused="false" scrollable="false" long-clickable="false" password="false" selected="false" visible-to-user="true" bounds="[0,818][768,1102]" drawing-order="1" hint="" display-id="0">
                                <node index="0" text="" resource-id="" class="android.widget.FrameLayout" package="com.google.android.apps.maps" content-desc="" checkable="false" checked="false" clickable="false" enabled="true" focusable="false" focused="false" scrollable="false" long-clickable="false" password="false" selected="false" visible-to-user="true" bounds="[0,818][768,1102]" drawing-order="2" hint="" display-id="0">
                                  <node index="0" text="" resource-id="" class="android.widget.FrameLayout" package="com.google.android.apps.maps" content-desc="" checkable="false" checked="false" clickable="false" enabled="true" focusable="false" focused="false" scrollable="false" long-clickable="false" password="false" selected="false" visible-to-user="true" bounds="[0,818][768,1102]" drawing-order="1" hint="" display-id="0">
                                    <node index="0" text="" resource-id="" class="android.widget.FrameLayout" package="com.google.android.apps.maps" content-desc="" checkable="false" checked="false" clickable="false" enabled="true" focusable="false" focused="false" scrollable="false" long-clickable="false" password="false" selected="false" visible-to-user="true" bounds="[0,818][768,1102]" drawing-order="2" hint="" display-id="0">
                                      <node index="0" text="" resource-id="" class="android.widget.FrameLayout" package="com.google.android.apps.maps" content-desc="" checkable="false" checked="false" clickable="false" enabled="true" focusable="false" focused="false" scrollable="false" long-clickable="false" password="false" selected="false" visible-to-user="true" bounds="[0,818][768,1102]" drawing-order="1" hint="" display-id="0">
                                        <node index="0" text="" resource-id="com.google.android.apps.maps:id/recycler_view" class="android.support.v7.widget.RecyclerView" package="com.google.android.apps.maps" content-desc="" checkable="false" checked="false" clickable="false" enabled="true" focusable="true" focused="false" scrollable="true" long-clickable="false" password="false" selected="false" visible-to-user="true" bounds="[0,834][768,1102]" drawing-order="4" hint="" display-id="0">
                                          <node index="0" text="" resource-id="" class="android.widget.FrameLayout" package="com.google.android.apps.maps" content-desc="" checkable="false" checked="false" clickable="false" enabled="true" focusable="false" focused="false" scrollable="false" long-clickable="false" password="false" selected="false" visible-to-user="true" bounds="[32,834][316,1102]" drawing-order="1" hint="" display-id="0">
                                            <node index="0" text="" resource-id="" class="android.widget.FrameLayout" package="com.google.android.apps.maps" content-desc="" checkable="false" checked="false" clickable="false" enabled="true" focusable="false" focused="false" scrollable="false" long-clickable="false" password="false" selected="false" visible-to-user="true" bounds="[32,834][316,1102]" drawing-order="1" hint="" display-id="0">
                                              <node index="0" text="" resource-id="" class="android.widget.ImageView" package="com.google.android.apps.maps" content-desc="" checkable="false" checked="false" clickable="false" enabled="true" focusable="false" focused="false" scrollable="false" long-clickable="false" password="false" selected="false" visible-to-user="true" bounds="[32,834][316,1102]" drawing-order="1" hint="" display-id="0" />
                                            </node>
                                          </node>
                                          <node index="1" text="" resource-id="" class="android.widget.FrameLayout" package="com.google.android.apps.maps" content-desc="" checkable="false" checked="false" clickable="false" enabled="true" focusable="false" focused="false" scrollable="false" long-clickable="false" password="false" selected="false" visible-to-user="true" bounds="[332,834][616,1102]" drawing-order="2" hint="" display-id="0">
                                            <node index="0" text="" resource-id="" class="android.widget.FrameLayout" package="com.google.android.apps.maps" content-desc="" checkable="false" checked="false" clickable="false" enabled="true" focusable="false" focused="false" scrollable="false" long-clickable="false" password="false" selected="false" visible-to-user="true" bounds="[332,834][616,1102]" drawing-order="1" hint="" display-id="0">
                                              <node index="0" text="" resource-id="" class="android.widget.ImageView" package="com.google.android.apps.maps" content-desc="" checkable="false" checked="false" clickable="false" enabled="true" focusable="false" focused="false" scrollable="false" long-clickable="false" password="false" selected="false" visible-to-user="true" bounds="[332,834][616,1102]" drawing-order="1" hint="" display-id="0" />
                                            </node>
                                          </node>
                                          <node index="2" text="" resource-id="" class="android.widget.FrameLayout" package="com.google.android.apps.maps" content-desc="" checkable="false" checked="false" clickable="false" enabled="true" focusable="false" focused="false" scrollable="false" long-clickable="false" password="false" selected="false" visible-to-user="true" bounds="[632,834][768,1102]" drawing-order="3" hint="" display-id="0">
                                            <node index="0" text="" resource-id="" class="android.widget.FrameLayout" package="com.google.android.apps.maps" content-desc="" checkable="false" checked="false" clickable="false" enabled="true" focusable="false" focused="false" scrollable="false" long-clickable="false" password="false" selected="false" visible-to-user="true" bounds="[632,834][768,1102]" drawing-order="1" hint="" display-id="0">
                                              <node index="0" text="" resource-id="" class="android.widget.ImageView" package="com.google.android.apps.maps" content-desc="" checkable="false" checked="false" clickable="false" enabled="true" focusable="false" focused="false" scrollable="false" long-clickable="false" password="false" selected="false" visible-to-user="true" bounds="[632,834][768,1102]" drawing-order="1" hint="" display-id="0" />
                                            </node>
                                          </node>
                                        </node>
                                      </node>
                                    </node>
                                  </node>
                                </node>
                              </node>
                            </node>
                            <node index="2" text="" resource-id="" class="android.widget.FrameLayout" package="com.google.android.apps.maps" content-desc="" checkable="false" checked="false" clickable="false" enabled="true" focusable="false" focused="false" scrollable="false" long-clickable="false" password="false" selected="false" visible-to-user="true" bounds="[549,998][768,1102]" drawing-order="3" hint="" display-id="0">
                              <node index="0" text="" resource-id="" class="android.widget.FrameLayout" package="com.google.android.apps.maps" content-desc="" checkable="false" checked="false" clickable="false" enabled="true" focusable="false" focused="false" scrollable="false" long-clickable="false" password="false" selected="false" visible-to-user="true" bounds="[549,998][736,1094]" drawing-order="2" hint="" display-id="0">
                                <node index="0" text="Menu" resource-id="" class="android.widget.Button" package="com.google.android.apps.maps" content-desc="See the menu photos for Chen's Restaurant" checkable="false" checked="false" clickable="true" enabled="true" focusable="true" focused="false" scrollable="false" long-clickable="false" password="false" selected="false" visible-to-user="true" bounds="[549,998][736,1094]" drawing-order="1" hint="" display-id="0" />
                              </node>
                            </node>
                            <node index="3" text="" resource-id="" class="android.widget.LinearLayout" package="com.google.android.apps.maps" content-desc="" checkable="false" checked="false" clickable="false" enabled="true" focusable="false" focused="false" scrollable="false" long-clickable="false" password="false" selected="false" visible-to-user="true" bounds="[0,1102][768,1184]" drawing-order="4" hint="" display-id="0">
                              <node index="0" text="" resource-id="" class="android.widget.LinearLayout" package="com.google.android.apps.maps" content-desc="" checkable="false" checked="false" clickable="false" enabled="true" focusable="false" focused="false" scrollable="false" long-clickable="false" password="false" selected="false" visible-to-user="true" bounds="[0,1126][768,1184]" drawing-order="2" hint="" display-id="0">
                                <node index="1" text="" resource-id="" class="android.widget.LinearLayout" package="com.google.android.apps.maps" content-desc="" checkable="false" checked="false" clickable="false" enabled="true" focusable="false" focused="false" scrollable="false" long-clickable="false" password="false" selected="false" visible-to-user="true" bounds="[32,1126][736,1184]" drawing-order="1" hint="" display-id="0">
                                  <node index="0" text="" resource-id="" class="android.widget.LinearLayout" package="com.google.android.apps.maps" content-desc="" checkable="false" checked="false" clickable="false" enabled="true" focusable="false" focused="false" scrollable="false" long-clickable="false" password="false" selected="false" visible-to-user="true" bounds="[32,1126][736,1171]" drawing-order="1" hint="" display-id="0">
                                    <node index="0" text="Chen's Restaurant" resource-id="com.google.android.apps.maps:id/title" class="android.widget.TextView" package="com.google.android.apps.maps" content-desc="Chen's Restaurant" checkable="false" checked="false" clickable="false" enabled="true" focusable="false" focused="false" scrollable="false" long-clickable="false" password="false" selected="false" visible-to-user="true" bounds="[32,1126][736,1171]" drawing-order="2" hint="" display-id="0" />
                                  </node>
                                  <node index="1" text="" resource-id="" class="android.widget.FrameLayout" package="com.google.android.apps.maps" content-desc="" checkable="false" checked="false" clickable="false" enabled="true" focusable="false" focused="false" scrollable="false" long-clickable="false" password="false" selected="false" visible-to-user="true" bounds="[32,1171][736,1184]" drawing-order="3" hint="" display-id="0">
                                    <node index="0" text="" resource-id="" class="android.widget.LinearLayout" package="com.google.android.apps.maps" content-desc="" checkable="false" checked="false" clickable="false" enabled="true" focusable="false" focused="false" scrollable="false" long-clickable="false" password="false" selected="false" visible-to-user="true" bounds="[32,1171][736,1184]" drawing-order="1" hint="" display-id="0">
                                      <node index="0" text="" resource-id="" class="android.widget.LinearLayout" package="com.google.android.apps.maps" content-desc="" checkable="false" checked="false" clickable="false" enabled="true" focusable="false" focused="false" scrollable="false" long-clickable="false" password="false" selected="false" visible-to-user="true" bounds="[32,1171][295,1184]" drawing-order="1" hint="" display-id="0">
                                        <node index="0" text="" resource-id="" class="android.widget.LinearLayout" package="com.google.android.apps.maps" content-desc="" checkable="false" checked="false" clickable="false" enabled="true" focusable="false" focused="false" scrollable="false" long-clickable="false" password="false" selected="false" visible-to-user="true" bounds="[32,1171][295,1184]" drawing-order="2" hint="" display-id="0">
                                          <node index="0" text="4.3" resource-id="" class="android.widget.TextView" package="com.google.android.apps.maps" content-desc="" checkable="false" checked="false" clickable="false" enabled="true" focusable="false" focused="false" scrollable="false" long-clickable="false" password="false" selected="false" visible-to-user="true" bounds="[32,1171][81,1184]" drawing-order="1" hint="" display-id="0" />
                                          <node index="1" text="" resource-id="" class="android.view.ViewGroup" package="com.google.android.apps.maps" content-desc="4.3 stars" checkable="false" checked="false" clickable="false" enabled="true" focusable="false" focused="false" scrollable="false" long-clickable="false" password="false" selected="false" visible-to-user="true" bounds="[81,1171][217,1184]" drawing-order="2" hint="" display-id="0">
                                            <node index="0" text="" resource-id="" class="android.widget.ImageView" package="com.google.android.apps.maps" content-desc="" checkable="false" checked="false" clickable="false" enabled="true" focusable="false" focused="false" scrollable="false" long-clickable="false" password="false" selected="false" visible-to-user="true" bounds="[81,1171][107,1184]" drawing-order="1" hint="" display-id="0" />
                                            <node index="1" text="" resource-id="" class="android.widget.ImageView" package="com.google.android.apps.maps" content-desc="" checkable="false" checked="false" clickable="false" enabled="true" focusable="false" focused="false" scrollable="false" long-clickable="false" password="false" selected="false" visible-to-user="true" bounds="[107,1171][135,1184]" drawing-order="2" hint="" display-id="0" />
                                            <node index="2" text="" resource-id="" class="android.widget.ImageView" package="com.google.android.apps.maps" content-desc="" checkable="false" checked="false" clickable="false" enabled="true" focusable="false" focused="false" scrollable="false" long-clickable="false" password="false" selected="false" visible-to-user="true" bounds="[135,1171][163,1184]" drawing-order="3" hint="" display-id="0" />
                                            <node index="3" text="" resource-id="" class="android.widget.ImageView" package="com.google.android.apps.maps" content-desc="" checkable="false" checked="false" clickable="false" enabled="true" focusable="false" focused="false" scrollable="false" long-clickable="false" password="false" selected="false" visible-to-user="true" bounds="[163,1171][191,1184]" drawing-order="4" hint="" display-id="0" />
                                            <node index="4" text="" resource-id="" class="android.widget.ImageView" package="com.google.android.apps.maps" content-desc="" checkable="false" checked="false" clickable="false" enabled="true" focusable="false" focused="false" scrollable="false" long-clickable="false" password="false" selected="false" visible-to-user="true" bounds="[191,1171][217,1184]" drawing-order="5" hint="" display-id="0" />
                                          </node>
                                          <node index="2" text="(827)" resource-id="" class="android.widget.TextView" package="com.google.android.apps.maps" content-desc="827 ratings and reviews" checkable="false" checked="false" clickable="false" enabled="true" focusable="false" focused="false" scrollable="false" long-clickable="false" password="false" selected="false" visible-to-user="true" bounds="[225,1171][295,1184]" drawing-order="3" hint="" display-id="0" />
                                        </node>
                                      </node>
                                    </node>
                                  </node>
                                </node>
                              </node>
                            </node>
                          </node>
                        </node>
                      </node>
                    </node>
                  </node>
                  <node index="9" text="" resource-id="com.google.android.apps.maps:id/compass_container" class="android.widget.LinearLayout" package="com.google.android.apps.maps" content-desc="" checkable="false" checked="false" clickable="false" enabled="true" focusable="false" focused="false" scrollable="false" long-clickable="false" password="false" selected="false" visible-to-user="true" bounds="[0,286][768,506]" drawing-order="10" hint="" display-id="0">
                    <node index="0" text="" resource-id="com.google.android.apps.maps:id/above_compass_container" class="android.widget.LinearLayout" package="com.google.android.apps.maps" content-desc="" checkable="false" checked="false" clickable="false" enabled="true" focusable="false" focused="false" scrollable="false" long-clickable="false" password="false" selected="false" visible-to-user="true" bounds="[0,286][768,406]" drawing-order="1" hint="" display-id="0">
                      <node index="0" text="" resource-id="com.google.android.apps.maps:id/layers_fab_button" class="android.widget.FrameLayout" package="com.google.android.apps.maps" content-desc="" checkable="false" checked="false" clickable="false" enabled="true" focusable="false" focused="false" scrollable="false" long-clickable="false" password="false" selected="false" visible-to-user="true" bounds="[0,286][768,406]" drawing-order="1" hint="" display-id="0">
                        <node index="0" text="" resource-id="" class="android.widget.FrameLayout" package="com.google.android.apps.maps" content-desc="" checkable="false" checked="false" clickable="false" enabled="true" focusable="false" focused="false" scrollable="false" long-clickable="false" password="false" selected="false" visible-to-user="true" bounds="[0,298][768,406]" drawing-order="1" hint="" display-id="0">
                          <node index="0" text="" resource-id="" class="android.widget.FrameLayout" package="com.google.android.apps.maps" content-desc="" checkable="false" checked="false" clickable="false" enabled="true" focusable="false" focused="false" scrollable="false" long-clickable="false" password="false" selected="false" visible-to-user="true" bounds="[652,298][768,406]" drawing-order="1" hint="" display-id="0">
                            <node index="0" text="" resource-id="com.google.android.apps.maps:id/layers_fab" class="android.widget.FrameLayout" package="com.google.android.apps.maps" content-desc="Layers" checkable="false" checked="false" clickable="true" enabled="true" focusable="true" focused="false" scrollable="false" long-clickable="false" password="false" selected="false" visible-to-user="true" bounds="[652,298][768,406]" drawing-order="1" hint="" display-id="0">
                              <node index="0" text="" resource-id="com.google.android.apps.maps:id/fab_icon" class="android.widget.FrameLayout" package="com.google.android.apps.maps" content-desc="" checkable="false" checked="false" clickable="false" enabled="true" focusable="false" focused="false" scrollable="false" long-clickable="false" password="false" selected="false" visible-to-user="true" bounds="[652,298][744,390]" drawing-order="1" hint="" display-id="0">
                                <node index="0" text="" resource-id="" class="android.widget.FrameLayout" package="com.google.android.apps.maps" content-desc="" checkable="false" checked="false" clickable="false" enabled="true" focusable="false" focused="false" scrollable="false" long-clickable="false" password="false" selected="false" visible-to-user="true" bounds="[652,298][744,390]" drawing-order="1" hint="" display-id="0">
                                  <node index="0" text="" resource-id="" class="android.widget.ImageView" package="com.google.android.apps.maps" content-desc="" checkable="false" checked="false" clickable="false" enabled="true" focusable="false" focused="false" scrollable="false" long-clickable="false" password="false" selected="false" visible-to-user="true" bounds="[652,298][744,390]" drawing-order="1" hint="" display-id="0" />
                                </node>
                                <node index="1" text="" resource-id="" class="android.widget.FrameLayout" package="com.google.android.apps.maps" content-desc="" checkable="false" checked="false" clickable="false" enabled="true" focusable="false" focused="false" scrollable="false" long-clickable="false" password="false" selected="false" visible-to-user="true" bounds="[652,298][744,390]" drawing-order="2" hint="" display-id="0">
                                  <node index="0" text="" resource-id="" class="android.widget.ImageView" package="com.google.android.apps.maps" content-desc="" checkable="false" checked="false" clickable="false" enabled="true" focusable="false" focused="false" scrollable="false" long-clickable="false" password="false" selected="false" visible-to-user="true" bounds="[652,298][744,390]" drawing-order="1" hint="" display-id="0" />
                                </node>
                              </node>
                            </node>
                          </node>
                        </node>
                      </node>
                    </node>
                  </node>
                  <node index="10" text="" resource-id="com.google.android.apps.maps:id/on_map_refresh_action_container" class="android.widget.FrameLayout" package="com.google.android.apps.maps" content-desc="" checkable="false" checked="false" clickable="false" enabled="true" focusable="false" focused="false" scrollable="false" long-clickable="false" password="false" selected="false" visible-to-user="true" bounds="[244,296][524,392]" drawing-order="19" hint="" display-id="0" />
                  <node index="11" text="" resource-id="com.google.android.apps.maps:id/footer_container" class="android.widget.LinearLayout" package="com.google.android.apps.maps" content-desc="" checkable="false" checked="false" clickable="false" enabled="true" focusable="false" focused="false" scrollable="false" long-clickable="false" password="false" selected="false" visible-to-user="true" bounds="[0,1048][768,1184]" drawing-order="31" hint="" display-id="0">
                    <node index="0" text="" resource-id="" class="android.widget.RelativeLayout" package="com.google.android.apps.maps" content-desc="" checkable="false" checked="false" clickable="false" enabled="true" focusable="false" focused="false" scrollable="false" long-clickable="false" password="false" selected="false" visible-to-user="true" bounds="[0,1048][768,1184]" drawing-order="2" hint="" display-id="0">
                      <node index="0" text="View map" resource-id="" class="android.widget.Button" package="com.google.android.apps.maps" content-desc="Map view" checkable="false" checked="false" clickable="true" enabled="true" focusable="true" focused="false" scrollable="false" long-clickable="false" password="false" selected="false" visible-to-user="true" bounds="[453,1048][736,1160]" drawing-order="1" hint="" display-id="0" />
                    </node>
                  </node>
                  <node index="12" text="" resource-id="com.google.android.apps.maps:id/watermark_image" class="android.widget.ImageView" package="com.google.android.apps.maps" content-desc="" checkable="false" checked="false" clickable="false" enabled="true" focusable="false" focused="false" scrollable="false" long-clickable="false" password="false" selected="false" visible-to-user="true" bounds="[32,588][164,638]" drawing-order="5" hint="" display-id="0" />
                  <node index="14" text="" resource-id="com.google.android.apps.maps:id/on_map_secondary_action_button_container" class="android.widget.LinearLayout" package="com.google.android.apps.maps" content-desc="" checkable="false" checked="false" clickable="false" enabled="true" focusable="false" focused="false" scrollable="false" long-clickable="false" password="false" selected="false" visible-to-user="true" bounds="[616,506][768,658]" drawing-order="8" hint="" display-id="0">
                    <node index="0" text="" resource-id="com.google.android.apps.maps:id/qu_mylocation_container" class="android.widget.FrameLayout" package="com.google.android.apps.maps" content-desc="" checkable="false" checked="false" clickable="false" enabled="true" focusable="false" focused="false" scrollable="false" long-clickable="false" password="false" selected="false" visible-to-user="true" bounds="[616,506][768,648]" drawing-order="1" hint="" display-id="0">
                      <node index="0" text="" resource-id="com.google.android.apps.maps:id/mylocation_button" class="android.widget.FrameLayout" package="com.google.android.apps.maps" content-desc="Location services disabled. Enable location services to re-center map to your location." checkable="false" checked="false" clickable="true" enabled="true" focusable="true" focused="false" scrollable="false" long-clickable="false" password="false" selected="false" visible-to-user="true" bounds="[616,506][768,648]" drawing-order="1" hint="" display-id="0">
                        <node index="0" text="" resource-id="com.google.android.apps.maps:id/fab_icon" class="android.widget.FrameLayout" package="com.google.android.apps.maps" content-desc="" checkable="false" checked="false" clickable="false" enabled="true" focusable="false" focused="false" scrollable="false" long-clickable="false" password="false" selected="false" visible-to-user="true" bounds="[616,506][744,634]" drawing-order="1" hint="" display-id="0">
                          <node index="0" text="" resource-id="" class="android.widget.FrameLayout" package="com.google.android.apps.maps" content-desc="" checkable="false" checked="false" clickable="false" enabled="true" focusable="false" focused="false" scrollable="false" long-clickable="false" password="false" selected="false" visible-to-user="true" bounds="[616,506][744,634]" drawing-order="1" hint="" display-id="0">
                            <node index="0" text="" resource-id="" class="android.widget.ImageView" package="com.google.android.apps.maps" content-desc="" checkable="false" checked="false" clickable="false" enabled="true" focusable="false" focused="false" scrollable="false" long-clickable="false" password="false" selected="false" visible-to-user="true" bounds="[616,506][744,634]" drawing-order="1" hint="" display-id="0" />
                          </node>
                          <node index="1" text="" resource-id="" class="android.widget.FrameLayout" package="com.google.android.apps.maps" content-desc="" checkable="false" checked="false" clickable="false" enabled="true" focusable="false" focused="false" scrollable="false" long-clickable="false" password="false" selected="false" visible-to-user="true" bounds="[616,506][744,634]" drawing-order="2" hint="" display-id="0">
                            <node index="0" text="" resource-id="" class="android.widget.ImageView" package="com.google.android.apps.maps" content-desc="" checkable="false" checked="false" clickable="false" enabled="true" focusable="false" focused="false" scrollable="false" long-clickable="false" password="false" selected="false" visible-to-user="true" bounds="[616,506][744,634]" drawing-order="1" hint="" display-id="0" />
                          </node>
                        </node>
                      </node>
                    </node>
                  </node>
                </node>
              </node>
            </node>
          </node>
        </node>
      </node>
    </node>
  </node>
  <node index="0" text="" resource-id="" class="android.widget.FrameLayout" package="com.android.systemui" content-desc="" checkable="false" checked="false" clickable="false" enabled="true" focusable="false" focused="false" scrollable="false" long-clickable="false" password="false" selected="false" visible-to-user="true" bounds="[0,0][768,48]" drawing-order="0" hint="" display-id="0">
    <node index="0" text="" resource-id="com.android.systemui:id/status_bar_launch_animation_container" class="android.widget.FrameLayout" package="com.android.systemui" content-desc="" checkable="false" checked="false" clickable="false" enabled="true" focusable="false" focused="false" scrollable="false" long-clickable="false" password="false" selected="false" visible-to-user="true" bounds="[0,0][768,48]" drawing-order="1" hint="" display-id="0" />
    <node index="1" text="" resource-id="com.android.systemui:id/status_bar_container" class="android.widget.FrameLayout" package="com.android.systemui" content-desc="" checkable="false" checked="false" clickable="false" enabled="true" focusable="false" focused="false" scrollable="false" long-clickable="false" password="false" selected="false" visible-to-user="true" bounds="[0,0][768,48]" drawing-order="2" hint="" display-id="0">
      <node index="0" text="" resource-id="com.android.systemui:id/status_bar" class="android.widget.FrameLayout" package="com.android.systemui" content-desc="" checkable="false" checked="false" clickable="false" enabled="true" focusable="false" focused="false" scrollable="false" long-clickable="false" password="false" selected="false" visible-to-user="true" bounds="[0,0][768,48]" drawing-order="1" hint="" display-id="0">
        <node index="0" text="" resource-id="com.android.systemui:id/status_bar_contents" class="android.widget.LinearLayout" package="com.android.systemui" content-desc="" checkable="false" checked="false" clickable="false" enabled="true" focusable="false" focused="false" scrollable="false" long-clickable="false" password="false" selected="false" visible-to-user="true" bounds="[0,0][728,48]" drawing-order="2" hint="" display-id="0">
          <node index="0" text="" resource-id="" class="android.widget.FrameLayout" package="com.android.systemui" content-desc="" checkable="false" checked="false" clickable="false" enabled="true" focusable="false" focused="false" scrollable="false" long-clickable="false" password="false" selected="false" visible-to-user="true" bounds="[16,0][364,48]" drawing-order="1" hint="" display-id="0">
            <node index="0" text="" resource-id="com.android.systemui:id/status_bar_left_side" class="android.widget.LinearLayout" package="com.android.systemui" content-desc="" checkable="false" checked="false" clickable="false" enabled="true" focusable="false" focused="false" scrollable="false" long-clickable="false" password="false" selected="false" visible-to-user="true" bounds="[16,0][364,48]" drawing-order="2" hint="" display-id="0">
              <node index="0" text="6:16" resource-id="com.android.systemui:id/clock" class="android.widget.TextView" package="com.android.systemui" content-desc="6:16 PM" checkable="false" checked="false" clickable="false" enabled="true" focusable="false" focused="false" scrollable="false" long-clickable="false" password="false" selected="false" visible-to-user="true" bounds="[16,0][85,48]" drawing-order="2" hint="" display-id="0" />
              <node index="1" text="" resource-id="com.android.systemui:id/notification_icon_area" class="android.widget.FrameLayout" package="com.android.systemui" content-desc="" checkable="false" checked="false" clickable="false" enabled="true" focusable="false" focused="false" scrollable="false" long-clickable="false" password="false" selected="false" visible-to-user="true" bounds="[85,0][364,48]" drawing-order="4" hint="" display-id="0">
                <node index="0" text="" resource-id="com.android.systemui:id/notification_icon_area_inner" class="android.widget.LinearLayout" package="com.android.systemui" content-desc="" checkable="false" checked="false" clickable="false" enabled="true" focusable="false" focused="false" scrollable="false" long-clickable="false" password="false" selected="false" visible-to-user="true" bounds="[85,0][364,48]" drawing-order="1" hint="" display-id="0">
                  <node index="0" text="" resource-id="com.android.systemui:id/notificationIcons" class="android.widget.FrameLayout" package="com.android.systemui" content-desc="" checkable="false" checked="false" clickable="false" enabled="true" focusable="false" focused="false" scrollable="false" long-clickable="false" password="false" selected="false" visible-to-user="true" bounds="[85,0][364,48]" drawing-order="1" hint="" display-id="0">
                    <node index="0" text="" resource-id="" class="android.widget.ImageView" package="com.android.systemui" content-desc="Gmail notification: 50 new messages" checkable="false" checked="false" clickable="false" enabled="true" focusable="false" focused="false" scrollable="false" long-clickable="false" password="false" selected="false" visible-to-user="true" bounds="[85,0][129,48]" drawing-order="1" hint="" display-id="0" />
                    <node index="1" text="" resource-id="" class="android.widget.ImageView" package="com.android.systemui" content-desc="ATX notification: UIAutomator" checkable="false" checked="false" clickable="false" enabled="true" focusable="false" focused="false" scrollable="false" long-clickable="false" password="false" selected="false" visible-to-user="true" bounds="[129,0][173,48]" drawing-order="2" hint="" display-id="0" />
                    <node index="2" text="" resource-id="" class="android.widget.ImageView" package="com.android.systemui" content-desc="Settings notification: Virtual SD card" checkable="false" checked="false" clickable="false" enabled="true" focusable="false" focused="false" scrollable="false" long-clickable="false" password="false" selected="false" visible-to-user="true" bounds="[173,0][217,48]" drawing-order="3" hint="" display-id="0" />
                    <node index="3" text="" resource-id="" class="android.widget.ImageView" package="com.android.systemui" content-desc="Android System notification: Serial console enabled" checkable="false" checked="false" clickable="false" enabled="true" focusable="false" focused="false" scrollable="false" long-clickable="false" password="false" selected="false" visible-to-user="true" bounds="[217,0][261,48]" drawing-order="4" hint="" display-id="0" />
                    <node index="4" text="" resource-id="" class="android.widget.ImageView" package="com.android.systemui" content-desc="Google notification: Live Science" checkable="false" checked="false" clickable="false" enabled="true" focusable="false" focused="false" scrollable="false" long-clickable="false" password="false" selected="false" visible-to-user="true" bounds="[261,0][305,48]" drawing-order="5" hint="" display-id="0" />
                  </node>
                </node>
              </node>
            </node>
          </node>
          <node index="1" text="" resource-id="com.android.systemui:id/system_icon_area" class="android.widget.LinearLayout" package="com.android.systemui" content-desc="" checkable="false" checked="false" clickable="false" enabled="true" focusable="false" focused="false" scrollable="false" long-clickable="false" password="false" selected="false" visible-to-user="true" bounds="[364,0][712,48]" drawing-order="4" hint="" display-id="0">
            <node index="0" text="" resource-id="com.android.systemui:id/system_icons" class="android.widget.LinearLayout" package="com.android.systemui" content-desc="" checkable="false" checked="false" clickable="false" enabled="true" focusable="false" focused="false" scrollable="false" long-clickable="false" password="false" selected="false" visible-to-user="true" bounds="[364,0][712,48]" drawing-order="1" hint="" display-id="0">
              <node index="0" text="" resource-id="com.android.systemui:id/statusIcons" class="android.widget.LinearLayout" package="com.android.systemui" content-desc="" checkable="false" checked="false" clickable="false" enabled="true" focusable="false" focused="false" scrollable="false" long-clickable="false" password="false" selected="false" visible-to-user="true" bounds="[364,0][696,48]" drawing-order="1" hint="" display-id="0">
                <node index="0" text="" resource-id="com.android.systemui:id/wifi_combo" class="android.widget.FrameLayout" package="com.android.systemui" content-desc="Wifi signal full." checkable="false" checked="false" clickable="false" enabled="true" focusable="false" focused="false" scrollable="false" long-clickable="false" password="false" selected="false" visible-to-user="true" bounds="[619,2][654,46]" drawing-order="15" hint="" display-id="0">
                  <node index="0" text="" resource-id="com.android.systemui:id/wifi_group" class="android.widget.LinearLayout" package="com.android.systemui" content-desc="" checkable="false" checked="false" clickable="false" enabled="true" focusable="false" focused="false" scrollable="false" long-clickable="false" password="false" selected="false" visible-to-user="true" bounds="[624,2][654,46]" drawing-order="1" hint="" display-id="0">
                    <node index="0" text="" resource-id="com.android.systemui:id/wifi_combo" class="android.widget.FrameLayout" package="com.android.systemui" content-desc="" checkable="false" checked="false" clickable="false" enabled="true" focusable="false" focused="false" scrollable="false" long-clickable="false" password="false" selected="false" visible-to-user="true" bounds="[624,9][654,39]" drawing-order="2" hint="" display-id="0">
                      <node index="0" text="" resource-id="com.android.systemui:id/wifi_signal" class="android.widget.ImageView" package="com.android.systemui" content-desc="" checkable="false" checked="false" clickable="false" enabled="true" focusable="false" focused="false" scrollable="false" long-clickable="false" password="false" selected="false" visible-to-user="true" bounds="[624,9][654,39]" drawing-order="1" hint="" display-id="0" />
                    </node>
                  </node>
                </node>
                <node index="1" text="" resource-id="com.android.systemui:id/mobile_combo" class="android.widget.FrameLayout" package="com.android.systemui" content-desc="Phone two bars." checkable="false" checked="false" clickable="false" enabled="true" focusable="false" focused="false" scrollable="false" long-clickable="false" password="false" selected="false" visible-to-user="true" bounds="[654,2][684,46]" drawing-order="17" hint="" display-id="0">
                  <node index="0" text="" resource-id="com.android.systemui:id/mobile_group" class="android.widget.LinearLayout" package="com.android.systemui" content-desc="" checkable="false" checked="false" clickable="false" enabled="true" focusable="false" focused="false" scrollable="false" long-clickable="false" password="false" selected="false" visible-to-user="true" bounds="[654,2][684,46]" drawing-order="1" hint="" display-id="0">
                    <node index="0" text="" resource-id="" class="android.widget.FrameLayout" package="com.android.systemui" content-desc="" checkable="false" checked="false" clickable="false" enabled="true" focusable="false" focused="false" scrollable="false" long-clickable="false" password="false" selected="false" visible-to-user="true" bounds="[654,9][684,39]" drawing-order="4" hint="" display-id="0">
                      <node index="0" text="" resource-id="com.android.systemui:id/mobile_signal" class="android.widget.ImageView" package="com.android.systemui" content-desc="" checkable="false" checked="false" clickable="false" enabled="true" focusable="false" focused="false" scrollable="false" long-clickable="false" password="false" selected="false" visible-to-user="true" bounds="[654,9][684,39]" drawing-order="1" hint="" display-id="0" />
                    </node>
                  </node>
                </node>
              </node>
              <node index="1" text="" resource-id="com.android.systemui:id/battery" class="android.widget.LinearLayout" package="com.android.systemui" content-desc="Battery 100 percent." checkable="false" checked="false" clickable="false" enabled="true" focusable="false" focused="false" scrollable="false" long-clickable="false" password="false" selected="false" visible-to-user="true" bounds="[696,0][712,48]" drawing-order="2" hint="" display-id="0">
                <node index="0" text="" resource-id="" class="android.widget.ImageView" package="com.android.systemui" content-desc="" checkable="false" checked="false" clickable="false" enabled="true" focusable="false" focused="false" scrollable="false" long-clickable="false" password="false" selected="false" visible-to-user="true" bounds="[696,11][712,37]" drawing-order="1" hint="" display-id="0" />
              </node>
            </node>
          </node>
        </node>
      </node>
    </node>
  </node>
  <node index="0" text="" resource-id="com.android.systemui:id/navigation_bar_frame" class="android.widget.FrameLayout" package="com.android.systemui" content-desc="" checkable="false" checked="false" clickable="false" enabled="true" focusable="false" focused="false" scrollable="false" long-clickable="false" password="false" selected="false" visible-to-user="true" bounds="[0,1184][768,1280]" drawing-order="0" hint="" display-id="0">
    <node index="0" text="" resource-id="com.android.systemui:id/navigation_bar_view" class="android.widget.FrameLayout" package="com.android.systemui" content-desc="" checkable="false" checked="false" clickable="false" enabled="true" focusable="false" focused="false" scrollable="false" long-clickable="false" password="false" selected="false" visible-to-user="true" bounds="[0,1184][768,1280]" drawing-order="1" hint="" display-id="0">
      <node index="0" text="" resource-id="com.android.systemui:id/navigation_inflater" class="android.widget.FrameLayout" package="com.android.systemui" content-desc="" checkable="false" checked="false" clickable="false" enabled="true" focusable="false" focused="false" scrollable="false" long-clickable="false" password="false" selected="false" visible-to-user="true" bounds="[0,1184][768,1280]" drawing-order="1" hint="" display-id="0">
        <node index="0" text="" resource-id="com.android.systemui:id/horizontal" class="android.widget.FrameLayout" package="com.android.systemui" content-desc="" checkable="false" checked="false" clickable="false" enabled="true" focusable="false" focused="false" scrollable="false" long-clickable="false" password="false" selected="false" visible-to-user="true" bounds="[0,1184][768,1280]" drawing-order="1" hint="" display-id="0">
          <node index="0" text="" resource-id="com.android.systemui:id/nav_buttons" class="android.widget.FrameLayout" package="com.android.systemui" content-desc="" checkable="false" checked="false" clickable="false" enabled="true" focusable="false" focused="false" scrollable="false" long-clickable="false" password="false" selected="false" visible-to-user="true" bounds="[16,1184][752,1280]" drawing-order="1" hint="" display-id="0">
            <node index="0" text="" resource-id="com.android.systemui:id/ends_group" class="android.widget.LinearLayout" package="com.android.systemui" content-desc="" checkable="false" checked="false" clickable="false" enabled="true" focusable="false" focused="false" scrollable="false" long-clickable="false" password="false" selected="false" visible-to-user="true" bounds="[16,1184][752,1280]" drawing-order="1" hint="" display-id="0">
              <node index="0" text="" resource-id="" class="android.widget.RelativeLayout" package="com.android.systemui" content-desc="" checkable="false" checked="false" clickable="false" enabled="true" focusable="false" focused="false" scrollable="false" long-clickable="false" password="false" selected="false" visible-to-user="true" bounds="[16,1184][89,1280]" drawing-order="1" hint="" display-id="0" />
              <node index="1" text="" resource-id="" class="android.widget.RelativeLayout" package="com.android.systemui" content-desc="" checkable="false" checked="false" clickable="false" enabled="true" focusable="false" focused="false" scrollable="false" long-clickable="false" password="false" selected="false" visible-to-user="true" bounds="[89,1184][236,1280]" drawing-order="2" hint="" display-id="0">
                <node index="0" text="" resource-id="com.android.systemui:id/back" class="android.widget.ImageView" package="com.android.systemui" content-desc="Back" checkable="false" checked="false" clickable="true" enabled="true" focusable="true" focused="false" scrollable="false" long-clickable="false" password="false" selected="false" visible-to-user="true" bounds="[89,1184][236,1280]" drawing-order="1" hint="" display-id="0" />
              </node>
              <node index="2" text="" resource-id="" class="android.widget.RelativeLayout" package="com.android.systemui" content-desc="" checkable="false" checked="false" clickable="false" enabled="true" focusable="false" focused="false" scrollable="false" long-clickable="false" password="false" selected="false" visible-to-user="true" bounds="[530,1184][678,1280]" drawing-order="4" hint="" display-id="0">
                <node index="0" text="" resource-id="com.android.systemui:id/recent_apps" class="android.widget.ImageView" package="com.android.systemui" content-desc="Overview" checkable="false" checked="false" clickable="true" enabled="true" focusable="true" focused="false" scrollable="false" long-clickable="false" password="false" selected="false" visible-to-user="true" bounds="[530,1184][678,1280]" drawing-order="1" hint="" display-id="0" />
              </node>
              <node index="3" text="" resource-id="" class="android.widget.RelativeLayout" package="com.android.systemui" content-desc="" checkable="false" checked="false" clickable="false" enabled="true" focusable="false" focused="false" scrollable="false" long-clickable="false" password="false" selected="false" visible-to-user="true" bounds="[678,1184][752,1280]" drawing-order="5" hint="" display-id="0" />
            </node>
            <node index="1" text="" resource-id="com.android.systemui:id/center_group" class="android.widget.LinearLayout" package="com.android.systemui" content-desc="" checkable="false" checked="false" clickable="false" enabled="true" focusable="false" focused="false" scrollable="false" long-clickable="false" password="false" selected="false" visible-to-user="true" bounds="[304,1184][464,1280]" drawing-order="2" hint="" display-id="0">
              <node index="0" text="" resource-id="com.android.systemui:id/home" class="android.widget.FrameLayout" package="com.android.systemui" content-desc="" checkable="false" checked="false" clickable="true" enabled="true" focusable="true" focused="false" scrollable="false" long-clickable="true" password="false" selected="false" visible-to-user="true" bounds="[304,1184][464,1280]" drawing-order="1" hint="" display-id="0">
                <node index="0" text="" resource-id="com.android.systemui:id/home_button" class="android.widget.ImageView" package="com.android.systemui" content-desc="Home" checkable="false" checked="false" clickable="true" enabled="true" focusable="true" focused="false" scrollable="false" long-clickable="true" password="false" selected="false" visible-to-user="true" bounds="[304,1184][464,1280]" drawing-order="5" hint="" display-id="0" />
                <node index="1" text="" resource-id="" class="android.widget.RelativeLayout" package="com.android.systemui" content-desc="" checkable="false" checked="false" clickable="false" enabled="true" focusable="false" focused="false" scrollable="false" long-clickable="false" password="false" selected="false" visible-to-user="true" bounds="[304,1184][464,1280]" drawing-order="1" hint="" display-id="0" />
                <node index="2" text="" resource-id="com.android.systemui:id/white_cutout" class="android.widget.ImageView" package="com.android.systemui" content-desc="" checkable="false" checked="false" clickable="false" enabled="true" focusable="false" focused="false" scrollable="false" long-clickable="false" password="false" selected="false" visible-to-user="true" bounds="[352,1200][416,1264]" drawing-order="3" hint="" display-id="0" />
                <node index="3" text="" resource-id="com.android.systemui:id/white" class="android.widget.ImageView" package="com.android.systemui" content-desc="" checkable="false" checked="false" clickable="false" enabled="true" focusable="false" focused="false" scrollable="false" long-clickable="false" password="false" selected="false" visible-to-user="true" bounds="[352,1200][416,1264]" drawing-order="4" hint="" display-id="0" />
              </node>
            </node>
          </node>
        </node>
      </node>
    </node>
  </node>
</hierarchy>